{
"meta":{"test_sets":[],"test_metrics":[],"learn_metrics":[{"best_value":"Min","name":"RMSE"}],"launch_mode":"Train","parameters":"","iteration_count":1000,"learn_sets":["learn"],"name":"experiment"},
"iterations":[
{"learn":[14.59871775],"iteration":0,"passed_time":0.002103715964,"remaining_time":2.101612248},
{"learn":[14.22518863],"iteration":1,"passed_time":0.002784431035,"remaining_time":1.389431086},
{"learn":[13.8866124],"iteration":2,"passed_time":0.003416427192,"remaining_time":1.135392637},
{"learn":[13.52356875],"iteration":3,"passed_time":0.003984959257,"remaining_time":0.9922548551},
{"learn":[13.18870211],"iteration":4,"passed_time":0.004586259386,"remaining_time":0.9126656178},
{"learn":[12.9124226],"iteration":5,"passed_time":0.005144323862,"remaining_time":0.8522429864},
{"learn":[12.60003351],"iteration":6,"passed_time":0.005762265018,"remaining_time":0.8174184518},
{"learn":[12.32990573],"iteration":7,"passed_time":0.00633962883,"remaining_time":0.7861139749},
{"learn":[12.0660619],"iteration":8,"passed_time":0.006864763616,"remaining_time":0.7558867493},
{"learn":[11.77309809],"iteration":9,"passed_time":0.007605785536,"remaining_time":0.7529727681},
{"learn":[11.49227636],"iteration":10,"passed_time":0.008167719517,"remaining_time":0.7343522365},
{"learn":[11.26264833],"iteration":11,"passed_time":0.008734843121,"remaining_time":0.7191687503},
{"learn":[11.04260393],"iteration":12,"passed_time":0.009240564127,"remaining_time":0.701572061},
{"learn":[10.79916926],"iteration":13,"passed_time":0.009705947719,"remaining_time":0.6835760322},
{"learn":[10.5541002],"iteration":14,"passed_time":0.01016383274,"remaining_time":0.6674250163},
{"learn":[10.31918115],"iteration":15,"passed_time":0.01065661758,"remaining_time":0.6553819812},
{"learn":[10.10004441],"iteration":16,"passed_time":0.01118272966,"remaining_time":0.6466248971},
{"learn":[9.894556723],"iteration":17,"passed_time":0.01166446616,"remaining_time":0.6363614315},
{"learn":[9.690174082],"iteration":18,"passed_time":0.0122019674,"remaining_time":0.630006843},
{"learn":[9.506034866],"iteration":19,"passed_time":0.01269385376,"remaining_time":0.6219988342},
{"learn":[9.338524633],"iteration":20,"passed_time":0.01325944492,"remaining_time":0.6181426941},
{"learn":[9.170203312],"iteration":21,"passed_time":0.01398079707,"remaining_time":0.6215099787},
{"learn":[9.010299969],"iteration":22,"passed_time":0.01478057482,"remaining_time":0.6278531131},
{"learn":[8.843866678],"iteration":23,"passed_time":0.01567035357,"remaining_time":0.6372610451},
{"learn":[8.690548059],"iteration":24,"passed_time":0.01620026939,"remaining_time":0.6318105063},
{"learn":[8.555307687],"iteration":25,"passed_time":0.01670815278,"remaining_time":0.6259131082},
{"learn":[8.413851302],"iteration":26,"passed_time":0.01721394105,"remaining_time":0.6203394313},
{"learn":[8.29256019],"iteration":27,"passed_time":0.0177787547,"remaining_time":0.6171767703},
{"learn":[8.162193833],"iteration":28,"passed_time":0.01849785612,"remaining_time":0.6193592514},
{"learn":[8.040736294],"iteration":29,"passed_time":0.01910053208,"remaining_time":0.6175838707},
{"learn":[7.921220278],"iteration":30,"passed_time":0.01967304308,"remaining_time":0.6149412497},
{"learn":[7.809589039],"iteration":31,"passed_time":0.02037606766,"remaining_time":0.6163760466},
{"learn":[7.699675801],"iteration":32,"passed_time":0.02090977268,"remaining_time":0.6127197023},
{"learn":[7.60645267],"iteration":33,"passed_time":0.02147519167,"remaining_time":0.6101480927},
{"learn":[7.498880302],"iteration":34,"passed_time":0.02199323847,"remaining_time":0.6063850036},
{"learn":[7.401158744],"iteration":35,"passed_time":0.02256308112,"remaining_time":0.6041891722},
{"learn":[7.306431077],"iteration":36,"passed_time":0.02318013433,"remaining_time":0.6033099827},
{"learn":[7.223863468],"iteration":37,"passed_time":0.02379033849,"remaining_time":0.6022712006},
{"learn":[7.143477682],"iteration":38,"passed_time":0.02433848149,"remaining_time":0.5997251465},
{"learn":[7.062817131],"iteration":39,"passed_time":0.02493111401,"remaining_time":0.5983467362},
{"learn":[6.990793435],"iteration":40,"passed_time":0.02552632352,"remaining_time":0.5970669331},
{"learn":[6.931862224],"iteration":41,"passed_time":0.02607711279,"remaining_time":0.594806525},
{"learn":[6.858296558],"iteration":42,"passed_time":0.02660702108,"remaining_time":0.5921609111},
{"learn":[6.786268161],"iteration":43,"passed_time":0.02708875558,"remaining_time":0.5885647803},
{"learn":[6.717118549],"iteration":44,"passed_time":0.02772142384,"remaining_time":0.5883102171},
{"learn":[6.652948106],"iteration":45,"passed_time":0.02825208907,"remaining_time":0.5859237603},
{"learn":[6.589686076],"iteration":46,"passed_time":0.02926958606,"remaining_time":0.5934875642},
{"learn":[6.531283097],"iteration":47,"passed_time":0.03008130462,"remaining_time":0.5966125416},
{"learn":[6.471368031],"iteration":48,"passed_time":0.03061093685,"remaining_time":0.59410206},
{"learn":[6.416481395],"iteration":49,"passed_time":0.03129611071,"remaining_time":0.5946261034},
{"learn":[6.369870822],"iteration":50,"passed_time":0.03218489961,"remaining_time":0.5988915634},
{"learn":[6.325678067],"iteration":51,"passed_time":0.03281558168,"remaining_time":0.5982532967},
{"learn":[6.275766122],"iteration":52,"passed_time":0.03344734694,"remaining_time":0.5976346707},
{"learn":[6.224773967],"iteration":53,"passed_time":0.0340730271,"remaining_time":0.5969089563},
{"learn":[6.182249254],"iteration":54,"passed_time":0.03463952779,"remaining_time":0.5951700684},
{"learn":[6.139904173],"iteration":55,"passed_time":0.03529775165,"remaining_time":0.5950192421},
{"learn":[6.100525536],"iteration":56,"passed_time":0.03582309374,"remaining_time":0.592652235},
{"learn":[6.062568564],"iteration":57,"passed_time":0.03640663199,"remaining_time":0.5912939196},
{"learn":[6.030559288],"iteration":58,"passed_time":0.03703880534,"remaining_time":0.5907375563},
{"learn":[5.997931376],"iteration":59,"passed_time":0.03754813684,"remaining_time":0.5882541439},
{"learn":[5.964103835],"iteration":60,"passed_time":0.03805159457,"remaining_time":0.5857450378},
{"learn":[5.933729724],"iteration":61,"passed_time":0.03878922886,"remaining_time":0.5868434947},
{"learn":[5.901932711],"iteration":62,"passed_time":0.03930051745,"remaining_time":0.5845172199},
{"learn":[5.873727795],"iteration":63,"passed_time":0.0398406238,"remaining_time":0.582669123},
{"learn":[5.846485734],"iteration":64,"passed_time":0.04038726498,"remaining_time":0.5809552731},
{"learn":[5.820630862],"iteration":65,"passed_time":0.0408839896,"remaining_time":0.5785703982},
{"learn":[5.793646238],"iteration":66,"passed_time":0.04134635147,"remaining_time":0.575763372},
{"learn":[5.765388646],"iteration":67,"passed_time":0.04187980753,"remaining_time":0.5739997149},
{"learn":[5.747073912],"iteration":68,"passed_time":0.04243394176,"remaining_time":0.5725507214},
{"learn":[5.722315217],"iteration":69,"passed_time":0.04299673005,"remaining_time":0.5712422707},
{"learn":[5.699970599],"iteration":70,"passed_time":0.04386135225,"remaining_time":0.5739041724},
{"learn":[5.682732647],"iteration":71,"passed_time":0.04464090358,"remaining_time":0.5753716461},
{"learn":[5.663525791],"iteration":72,"passed_time":0.04522678291,"remaining_time":0.5743181884},
{"learn":[5.642381613],"iteration":73,"passed_time":0.045840967,"remaining_time":0.57363156},
{"learn":[5.621404779],"iteration":74,"passed_time":0.04645626942,"remaining_time":0.5729606562},
{"learn":[5.602460129],"iteration":75,"passed_time":0.04707152014,"remaining_time":0.572290587},
{"learn":[5.587337574],"iteration":76,"passed_time":0.04772792043,"remaining_time":0.5721152021},
{"learn":[5.572393026],"iteration":77,"passed_time":0.04826482586,"remaining_time":0.5705149929},
{"learn":[5.558425806],"iteration":78,"passed_time":0.04882753334,"remaining_time":0.5692425089},
{"learn":[5.541518902],"iteration":79,"passed_time":0.04951388376,"remaining_time":0.5694096633},
{"learn":[5.526157283],"iteration":80,"passed_time":0.05006929646,"remaining_time":0.568070166},
{"learn":[5.511746977],"iteration":81,"passed_time":0.05060722937,"remaining_time":0.5665541044},
{"learn":[5.504975022],"iteration":82,"passed_time":0.05088942211,"remaining_time":0.5622361455},
{"learn":[5.493980522],"iteration":83,"passed_time":0.05138302915,"remaining_time":0.5603196988},
{"learn":[5.480745463],"iteration":84,"passed_time":0.05188202005,"remaining_time":0.5584946865},
{"learn":[5.464052013],"iteration":85,"passed_time":0.0523421819,"remaining_time":0.5562878402},
{"learn":[5.449143727],"iteration":86,"passed_time":0.052875522,"remaining_time":0.5548890987},
{"learn":[5.438255432],"iteration":87,"passed_time":0.0533852124,"remaining_time":0.5532649285},
{"learn":[5.425927931],"iteration":88,"passed_time":0.05388068517,"remaining_time":0.5515202718},
{"learn":[5.412331217],"iteration":89,"passed_time":0.05439581416,"remaining_time":0.5500021209},
{"learn":[5.400691499],"iteration":90,"passed_time":0.05487176523,"remaining_time":0.5481146658},
{"learn":[5.391618744],"iteration":91,"passed_time":0.05535869888,"remaining_time":0.546366289},
{"learn":[5.380766572],"iteration":92,"passed_time":0.05583300758,"remaining_time":0.5445219127},
{"learn":[5.372207183],"iteration":93,"passed_time":0.05643955205,"remaining_time":0.5439812144},
{"learn":[5.362918837],"iteration":94,"passed_time":0.05701609869,"remaining_time":0.5431533612},
{"learn":[5.348292324],"iteration":95,"passed_time":0.05765244321,"remaining_time":0.5428938402},
{"learn":[5.339772295],"iteration":96,"passed_time":0.05879889875,"remaining_time":0.5473753152},
{"learn":[5.331515983],"iteration":97,"passed_time":0.05933266451,"remaining_time":0.5461026876},
{"learn":[5.323861644],"iteration":98,"passed_time":0.05995660643,"remaining_time":0.5456656808},
{"learn":[5.313277281],"iteration":99,"passed_time":0.06057207149,"remaining_time":0.5451486434},
{"learn":[5.30685627],"iteration":100,"passed_time":0.06137413561,"remaining_time":0.5462905734},
{"learn":[5.29652059],"iteration":101,"passed_time":0.06232371574,"remaining_time":0.5486931053},
{"learn":[5.288350766],"iteration":102,"passed_time":0.06289381338,"remaining_time":0.547725734},
{"learn":[5.27993346],"iteration":103,"passed_time":0.06356720254,"remaining_time":0.5476558988},
{"learn":[5.271789139],"iteration":104,"passed_time":0.06419620158,"remaining_time":0.5471961944},
{"learn":[5.262684686],"iteration":105,"passed_time":0.0649671646,"remaining_time":0.5479306146},
{"learn":[5.251619772],"iteration":106,"passed_time":0.06634072026,"remaining_time":0.5536660112},
{"learn":[5.241012171],"iteration":107,"passed_time":0.0670333922,"remaining_time":0.5536461652},
{"learn":[5.232684032],"iteration":108,"passed_time":0.06751134754,"remaining_time":0.5518588134},
{"learn":[5.224267141],"iteration":109,"passed_time":0.06808861397,"remaining_time":0.5508987858},
{"learn":[5.216324968],"iteration":110,"passed_time":0.06864745998,"remaining_time":0.5497981254},
{"learn":[5.211102527],"iteration":111,"passed_time":0.06920053511,"remaining_time":0.5486613855},
{"learn":[5.206364257],"iteration":112,"passed_time":0.06969423952,"remaining_time":0.5470689421},
{"learn":[5.196937641],"iteration":113,"passed_time":0.07025817626,"remaining_time":0.5460416155},
{"learn":[5.190746047],"iteration":114,"passed_time":0.07140503136,"remaining_time":0.5495082848},
{"learn":[5.181885213],"iteration":115,"passed_time":0.07241687142,"remaining_time":0.5518665029},
{"learn":[5.178293568],"iteration":116,"passed_time":0.07350913935,"remaining_time":0.5547741029},
{"learn":[5.170991438],"iteration":117,"passed_time":0.07403847291,"remaining_time":0.5534062128},
{"learn":[5.166257212],"iteration":118,"passed_time":0.07462214519,"remaining_time":0.5524547051},
{"learn":[5.161421246],"iteration":119,"passed_time":0.0751714,"remaining_time":0.5512569333},
{"learn":[5.158223542],"iteration":120,"passed_time":0.0758513481,"remaining_time":0.5510192974},
{"learn":[5.15470988],"iteration":121,"passed_time":0.07634025641,"remaining_time":0.5493995502},
{"learn":[5.146388143],"iteration":122,"passed_time":0.07694103803,"remaining_time":0.5485958565},
{"learn":[5.139529364],"iteration":123,"passed_time":0.07749736477,"remaining_time":0.5474813834},
{"learn":[5.134276023],"iteration":124,"passed_time":0.07806872831,"remaining_time":0.5464810982},
{"learn":[5.128536065],"iteration":125,"passed_time":0.07864357637,"remaining_time":0.5455117916},
{"learn":[5.123300353],"iteration":126,"passed_time":0.07901441083,"remaining_time":0.5431463044},
{"learn":[5.116200518],"iteration":127,"passed_time":0.07951514801,"remaining_time":0.5416969459},
{"learn":[5.108728704],"iteration":128,"passed_time":0.08003703822,"remaining_time":0.5404051185},
{"learn":[5.104075866],"iteration":129,"passed_time":0.08055038982,"remaining_time":0.5390679934},
{"learn":[5.100317606],"iteration":130,"passed_time":0.0812406504,"remaining_time":0.5389169862},
{"learn":[5.095814182],"iteration":131,"passed_time":0.08176514571,"remaining_time":0.5376677763},
{"learn":[5.092146915],"iteration":132,"passed_time":0.08225523108,"remaining_time":0.536205153},
{"learn":[5.085258329],"iteration":133,"passed_time":0.08271843121,"remaining_time":0.5345832942},
{"learn":[5.079219421],"iteration":134,"passed_time":0.08321758726,"remaining_time":0.533208985},
{"learn":[5.076476829],"iteration":135,"passed_time":0.08377271786,"remaining_time":0.5322031488},
{"learn":[5.072133867],"iteration":136,"passed_time":0.0843398761,"remaining_time":0.5312796575},
{"learn":[5.067031564],"iteration":137,"passed_time":0.08494303242,"remaining_time":0.530586188},
{"learn":[5.061358312],"iteration":138,"passed_time":0.0856139224,"remaining_time":0.5303135769},
{"learn":[5.056759124],"iteration":139,"passed_time":0.08636068458,"remaining_time":0.5305013481},
{"learn":[5.050254],"iteration":140,"passed_time":0.08694781827,"remaining_time":0.5297033751},
{"learn":[5.048376474],"iteration":141,"passed_time":0.08739015851,"remaining_time":0.528033493},
{"learn":[5.042603751],"iteration":142,"passed_time":0.08800479234,"remaining_time":0.5274133359},
{"learn":[5.037477349],"iteration":143,"passed_time":0.08857844727,"remaining_time":0.5265496588},
{"learn":[5.03230489],"iteration":144,"passed_time":0.08916588615,"remaining_time":0.5257712597},
{"learn":[5.025976187],"iteration":145,"passed_time":0.08970142679,"remaining_time":0.5246919074},
{"learn":[5.01952451],"iteration":146,"passed_time":0.09025820728,"remaining_time":0.5237432028},
{"learn":[5.017569424],"iteration":147,"passed_time":0.09081994902,"remaining_time":0.5228283552},
{"learn":[5.008962367],"iteration":148,"passed_time":0.09135524621,"remaining_time":0.5217672116},
{"learn":[5.003880266],"iteration":149,"passed_time":0.09187725939,"remaining_time":0.5206378032},
{"learn":[4.996387564],"iteration":150,"passed_time":0.09236345619,"remaining_time":0.5193150616},
{"learn":[4.993361683],"iteration":151,"passed_time":0.09287715915,"remaining_time":0.5181567826},
{"learn":[4.99005752],"iteration":152,"passed_time":0.09337212796,"remaining_time":0.5169032182},
{"learn":[4.986908764],"iteration":153,"passed_time":0.09386838628,"remaining_time":0.5156665895},
{"learn":[4.985207175],"iteration":154,"passed_time":0.09481051251,"remaining_time":0.5168702134},
{"learn":[4.979003494],"iteration":155,"passed_time":0.09539360654,"remaining_time":0.5161038713},
{"learn":[4.973142217],"iteration":156,"passed_time":0.09590362722,"remaining_time":0.5149475016},
{"learn":[4.967056696],"iteration":157,"passed_time":0.09647143949,"remaining_time":0.5141072915},
{"learn":[4.961460696],"iteration":158,"passed_time":0.09706149803,"remaining_time":0.5133881751},
{"learn":[4.954240363],"iteration":159,"passed_time":0.09758436954,"remaining_time":0.5123179401},
{"learn":[4.952320707],"iteration":160,"passed_time":0.09797361239,"remaining_time":0.5105581416},
{"learn":[4.948337777],"iteration":161,"passed_time":0.09848805873,"remaining_time":0.5094629211},
{"learn":[4.943228639],"iteration":162,"passed_time":0.09902403455,"remaining_time":0.5084853799},
{"learn":[4.938545759],"iteration":163,"passed_time":0.1000143722,"remaining_time":0.5098293609},
{"learn":[4.935330572],"iteration":164,"passed_time":0.1009872688,"remaining_time":0.5110567844},
{"learn":[4.932051543],"iteration":165,"passed_time":0.1021363339,"remaining_time":0.5131427862},
{"learn":[4.928964153],"iteration":166,"passed_time":0.1026450957,"remaining_time":0.5119961961},
{"learn":[4.922860227],"iteration":167,"passed_time":0.1031985604,"remaining_time":0.5110785847},
{"learn":[4.917668772],"iteration":168,"passed_time":0.1037274261,"remaining_time":0.5100443261},
{"learn":[4.910365386],"iteration":169,"passed_time":0.1042761007,"remaining_time":0.5091127269},
{"learn":[4.906457206],"iteration":170,"passed_time":0.1055888481,"remaining_time":0.5118897956},
{"learn":[4.901996508],"iteration":171,"passed_time":0.1061752449,"remaining_time":0.5111226906},
{"learn":[4.896816173],"iteration":172,"passed_time":0.1068552793,"remaining_time":0.5108052949},
{"learn":[4.891123132],"iteration":173,"passed_time":0.1074138021,"remaining_time":0.5099068996},
{"learn":[4.887630202],"iteration":174,"passed_time":0.1079715579,"remaining_time":0.5090087728},
{"learn":[4.885259712],"iteration":175,"passed_time":0.1085402992,"remaining_time":0.5081659465},
{"learn":[4.880659728],"iteration":176,"passed_time":0.1090905494,"remaining_time":0.5072402383},
{"learn":[4.877299723],"iteration":177,"passed_time":0.1095746596,"remaining_time":0.5060133158},
{"learn":[4.874038772],"iteration":178,"passed_time":0.1101851956,"remaining_time":0.5053745562},
{"learn":[4.86943698],"iteration":179,"passed_time":0.1108580552,"remaining_time":0.5050200292},
{"learn":[4.861268711],"iteration":180,"passed_time":0.1114907054,"remaining_time":0.5044800426},
{"learn":[4.858673056],"iteration":181,"passed_time":0.1121244995,"remaining_time":0.5039441791},
{"learn":[4.854036207],"iteration":182,"passed_time":0.1126603293,"remaining_time":0.5029698853},
{"learn":[4.85130244],"iteration":183,"passed_time":0.1131632153,"remaining_time":0.501854259},
{"learn":[4.847510084],"iteration":184,"passed_time":0.1136962607,"remaining_time":0.5008781216},
{"learn":[4.845691673],"iteration":185,"passed_time":0.114217653,"remaining_time":0.4998557503},
{"learn":[4.842058646],"iteration":186,"passed_time":0.1149337197,"remaining_time":0.4996851021},
{"learn":[4.838623675],"iteration":187,"passed_time":0.1159764666,"remaining_time":0.5009196322},
{"learn":[4.834602161],"iteration":188,"passed_time":0.1167360645,"remaining_time":0.5009150705},
{"learn":[4.830858976],"iteration":189,"passed_time":0.1172815181,"remaining_time":0.4999896298},
{"learn":[4.827590511],"iteration":190,"passed_time":0.1178011019,"remaining_time":0.4989585937},
{"learn":[4.822246226],"iteration":191,"passed_time":0.1183144444,"remaining_time":0.4979066202},
{"learn":[4.816686395],"iteration":192,"passed_time":0.1188797946,"remaining_time":0.4970776905},
{"learn":[4.814797121],"iteration":193,"passed_time":0.1194925713,"remaining_time":0.4964485177},
{"learn":[4.811639392],"iteration":194,"passed_time":0.1201297942,"remaining_time":0.4959204324},
{"learn":[4.804813432],"iteration":195,"passed_time":0.1207853266,"remaining_time":0.4954663398},
{"learn":[4.80251613],"iteration":196,"passed_time":0.1213142616,"remaining_time":0.4944941731},
{"learn":[4.800087884],"iteration":197,"passed_time":0.1218802222,"remaining_time":0.4936764557},
{"learn":[4.794773135],"iteration":198,"passed_time":0.1223911951,"remaining_time":0.4926399361},
{"learn":[4.791664833],"iteration":199,"passed_time":0.1228915789,"remaining_time":0.4915663157},
{"learn":[4.785989873],"iteration":200,"passed_time":0.1240235192,"remaining_time":0.4930089145},
{"learn":[4.782387142],"iteration":201,"passed_time":0.1245226772,"remaining_time":0.49192622},
{"learn":[4.778623704],"iteration":202,"passed_time":0.1250543835,"remaining_time":0.4909770623},
{"learn":[4.775772178],"iteration":203,"passed_time":0.1257130436,"remaining_time":0.490527366},
{"learn":[4.77023101],"iteration":204,"passed_time":0.1263094838,"remaining_time":0.4898343398},
{"learn":[4.764496689],"iteration":205,"passed_time":0.1268310548,"remaining_time":0.4888536773},
{"learn":[4.763138716],"iteration":206,"passed_time":0.1273612347,"remaining_time":0.4879104303},
{"learn":[4.758053283],"iteration":207,"passed_time":0.1279810792,"remaining_time":0.4873125708},
{"learn":[4.755063788],"iteration":208,"passed_time":0.1284661265,"remaining_time":0.4862043353},
{"learn":[4.752465267],"iteration":209,"passed_time":0.1290826688,"remaining_time":0.4855967063},
{"learn":[4.748067377],"iteration":210,"passed_time":0.1300892981,"remaining_time":0.4864476598},
{"learn":[4.744163298],"iteration":211,"passed_time":0.1308090551,"remaining_time":0.4862147896},
{"learn":[4.736670896],"iteration":212,"passed_time":0.1314890122,"remaining_time":0.4858302939},
{"learn":[4.73349255],"iteration":213,"passed_time":0.1320208379,"remaining_time":0.4848989655},
{"learn":[4.731864595],"iteration":214,"passed_time":0.1326383896,"remaining_time":0.4842843527},
{"learn":[4.728398311],"iteration":215,"passed_time":0.1333646924,"remaining_time":0.4840644392},
{"learn":[4.723865975],"iteration":216,"passed_time":0.133965077,"remaining_time":0.4833855083},
{"learn":[4.723483365],"iteration":217,"passed_time":0.1344975759,"remaining_time":0.4824637813},
{"learn":[4.72095416],"iteration":218,"passed_time":0.1350369719,"remaining_time":0.4815702059},
{"learn":[4.716173382],"iteration":219,"passed_time":0.1355693814,"remaining_time":0.4806550796},
{"learn":[4.710563974],"iteration":220,"passed_time":0.1362739159,"remaining_time":0.4803501378},
{"learn":[4.707160263],"iteration":221,"passed_time":0.1368070833,"remaining_time":0.4794410397},
{"learn":[4.70408351],"iteration":222,"passed_time":0.1373382209,"remaining_time":0.4785282404},
{"learn":[4.702501831],"iteration":223,"passed_time":0.1378486295,"remaining_time":0.4775470381},
{"learn":[4.700269738],"iteration":224,"passed_time":0.1383423852,"remaining_time":0.47651266},
{"learn":[4.695346302],"iteration":225,"passed_time":0.1388462786,"remaining_time":0.4755177859},
{"learn":[4.689769299],"iteration":226,"passed_time":0.1393298627,"remaining_time":0.4744580789},
{"learn":[4.687919514],"iteration":227,"passed_time":0.1397861616,"remaining_time":0.4733110384},
{"learn":[4.682982074],"iteration":228,"passed_time":0.1402545097,"remaining_time":0.4722105981},
{"learn":[4.679578702],"iteration":229,"passed_time":0.1407477117,"remaining_time":0.4711988608},
{"learn":[4.675751423],"iteration":230,"passed_time":0.1412594068,"remaining_time":0.4702531769},
{"learn":[4.672710726],"iteration":231,"passed_time":0.1417790287,"remaining_time":0.4693374744},
{"learn":[4.6690533],"iteration":232,"passed_time":0.1422931242,"remaining_time":0.4684069797},
{"learn":[4.667595702],"iteration":233,"passed_time":0.1430124831,"remaining_time":0.4681519747},
{"learn":[4.664241291],"iteration":234,"passed_time":0.1435141429,"remaining_time":0.4671843375},
{"learn":[4.662246999],"iteration":235,"passed_time":0.1440721351,"remaining_time":0.4664030136},
{"learn":[4.658668443],"iteration":236,"passed_time":0.1449478659,"remaining_time":0.4666465049},
{"learn":[4.658017572],"iteration":237,"passed_time":0.1457583963,"remaining_time":0.4666718403},
{"learn":[4.657656705],"iteration":238,"passed_time":0.1463835575,"remaining_time":0.4660999466},
{"learn":[4.653242871],"iteration":239,"passed_time":0.1469696551,"remaining_time":0.465403908},
{"learn":[4.6507302],"iteration":240,"passed_time":0.1476793646,"remaining_time":0.465098082},
{"learn":[4.647671336],"iteration":241,"passed_time":0.1482707428,"remaining_time":0.464418277},
{"learn":[4.645506007],"iteration":242,"passed_time":0.1488630526,"remaining_time":0.463742102},
{"learn":[4.641297906],"iteration":243,"passed_time":0.1494481177,"remaining_time":0.4630441681},
{"learn":[4.63798107],"iteration":244,"passed_time":0.1500665885,"remaining_time":0.4624500991},
{"learn":[4.635062318],"iteration":245,"passed_time":0.1506499761,"remaining_time":0.4617483008},
{"learn":[4.631606017],"iteration":246,"passed_time":0.1511913353,"remaining_time":0.460919334},
{"learn":[4.630215494],"iteration":247,"passed_time":0.1517028874,"remaining_time":0.4600023039},
{"learn":[4.62729814],"iteration":248,"passed_time":0.1522097715,"remaining_time":0.4590744513},
{"learn":[4.624691756],"iteration":249,"passed_time":0.1526477337,"remaining_time":0.4579432012},
{"learn":[4.621840053],"iteration":250,"passed_time":0.1531282279,"remaining_time":0.4569443932},
{"learn":[4.619602091],"iteration":251,"passed_time":0.1535917252,"remaining_time":0.4558992478},
{"learn":[4.613584029],"iteration":252,"passed_time":0.154070329,"remaining_time":0.4549033035},
{"learn":[4.6119388],"iteration":253,"passed_time":0.1545954036,"remaining_time":0.4540479176},
{"learn":[4.60870702],"iteration":254,"passed_time":0.1550811371,"remaining_time":0.4530801848},
{"learn":[4.604771557],"iteration":255,"passed_time":0.1556923647,"remaining_time":0.452480935},
{"learn":[4.604231277],"iteration":256,"passed_time":0.1562133213,"remaining_time":0.4516206137},
{"learn":[4.600750354],"iteration":257,"passed_time":0.1567317877,"remaining_time":0.4507557616},
{"learn":[4.596488253],"iteration":258,"passed_time":0.1573081246,"remaining_time":0.4500591517},
{"learn":[4.59470784],"iteration":259,"passed_time":0.1579279761,"remaining_time":0.4494873167},
{"learn":[4.588818005],"iteration":260,"passed_time":0.1586809303,"remaining_time":0.4492919828},
{"learn":[4.585054174],"iteration":261,"passed_time":0.1595925091,"remaining_time":0.449539205},
{"learn":[4.581471435],"iteration":262,"passed_time":0.1601570361,"remaining_time":0.4488050784},
{"learn":[4.577555199],"iteration":263,"passed_time":0.1606659967,"remaining_time":0.4479173241},
{"learn":[4.57457145],"iteration":264,"passed_time":0.1612851726,"remaining_time":0.4473381203},
{"learn":[4.573029224],"iteration":265,"passed_time":0.1618424802,"remaining_time":0.4465878964},
{"learn":[4.571326203],"iteration":266,"passed_time":0.1624070368,"remaining_time":0.4458590187},
{"learn":[4.571019224],"iteration":267,"passed_time":0.1630377801,"remaining_time":0.4453121457},
{"learn":[4.565766631],"iteration":268,"passed_time":0.1637135465,"remaining_time":0.4448869981},
{"learn":[4.563383471],"iteration":269,"passed_time":0.1642271094,"remaining_time":0.444021444},
{"learn":[4.558165805],"iteration":270,"passed_time":0.1648615922,"remaining_time":0.4434837665},
{"learn":[4.55629209],"iteration":271,"passed_time":0.1653902592,"remaining_time":0.4426621644},
{"learn":[4.549383848],"iteration":272,"passed_time":0.1659208261,"remaining_time":0.4418477676},
{"learn":[4.546227503],"iteration":273,"passed_time":0.1664289373,"remaining_time":0.4409759434},
{"learn":[4.540620977],"iteration":274,"passed_time":0.1669050942,"remaining_time":0.4400225211},
{"learn":[4.532898237],"iteration":275,"passed_time":0.167365244,"remaining_time":0.4390305676},
{"learn":[4.529757367],"iteration":276,"passed_time":0.1678428299,"remaining_time":0.438087964},
{"learn":[4.52579294],"iteration":277,"passed_time":0.1683298825,"remaining_time":0.437173292},
{"learn":[4.521572155],"iteration":278,"passed_time":0.1688523535,"remaining_time":0.4363532146},
{"learn":[4.518818099],"iteration":279,"passed_time":0.1693477585,"remaining_time":0.4354656647},
{"learn":[4.514012334],"iteration":280,"passed_time":0.1698441348,"remaining_time":0.4345833911},
{"learn":[4.508331416],"iteration":281,"passed_time":0.1703187978,"remaining_time":0.4336485704},
{"learn":[4.506038537],"iteration":282,"passed_time":0.1708761932,"remaining_time":0.4329266097},
{"learn":[4.505805643],"iteration":283,"passed_time":0.1713401749,"remaining_time":0.4319703},
{"learn":[4.501550352],"iteration":284,"passed_time":0.1718777128,"remaining_time":0.4312019811},
{"learn":[4.494692643],"iteration":285,"passed_time":0.1725892147,"remaining_time":0.430869578},
{"learn":[4.489330245],"iteration":286,"passed_time":0.1734090482,"remaining_time":0.4308036634},
{"learn":[4.484826955],"iteration":287,"passed_time":0.1742584489,"remaining_time":0.4308056098},
{"learn":[4.478285428],"iteration":288,"passed_time":0.1747784684,"remaining_time":0.4299913183},
{"learn":[4.475311671],"iteration":289,"passed_time":0.1753437087,"remaining_time":0.4292897695},
{"learn":[4.471581298],"iteration":290,"passed_time":0.1759727217,"remaining_time":0.4287445351},
{"learn":[4.469164956],"iteration":291,"passed_time":0.1765579179,"remaining_time":0.4280924859},
{"learn":[4.462068024],"iteration":292,"passed_time":0.1771729096,"remaining_time":0.4275127888},
{"learn":[4.458540976],"iteration":293,"passed_time":0.1778735465,"remaining_time":0.4271385163},
{"learn":[4.455757458],"iteration":294,"passed_time":0.1785204821,"remaining_time":0.4266336944},
{"learn":[4.453027414],"iteration":295,"passed_time":0.1790635313,"remaining_time":0.4258808312},
{"learn":[4.450659338],"iteration":296,"passed_time":0.1797042327,"remaining_time":0.4253605239},
{"learn":[4.444696901],"iteration":297,"passed_time":0.1802154244,"remaining_time":0.424534322},
{"learn":[4.442052813],"iteration":298,"passed_time":0.1807220379,"remaining_time":0.4236994935},
{"learn":[4.440036756],"iteration":299,"passed_time":0.1812472455,"remaining_time":0.4229102394},
{"learn":[4.435017051],"iteration":300,"passed_time":0.1816854703,"remaining_time":0.4219207432},
{"learn":[4.429962125],"iteration":301,"passed_time":0.1821662761,"remaining_time":0.4210333137},
{"learn":[4.427666256],"iteration":302,"passed_time":0.1826465871,"remaining_time":0.4201474298},
{"learn":[4.425030004],"iteration":303,"passed_time":0.1831311119,"remaining_time":0.4192738615},
{"learn":[4.422588771],"iteration":304,"passed_time":0.1836295206,"remaining_time":0.4184344813},
{"learn":[4.418936667],"iteration":305,"passed_time":0.1841205853,"remaining_time":0.4175806738},
{"learn":[4.416887976],"iteration":306,"passed_time":0.1846703752,"remaining_time":0.4168617915},
{"learn":[4.413773354],"iteration":307,"passed_time":0.1851481859,"remaining_time":0.4159822879},
{"learn":[4.411129391],"iteration":308,"passed_time":0.1856847084,"remaining_time":0.415236678},
{"learn":[4.40850819],"iteration":309,"passed_time":0.1862754285,"remaining_time":0.4146130505},
{"learn":[4.404880292],"iteration":310,"passed_time":0.1870862475,"remaining_time":0.4144772494},
{"learn":[4.404593827],"iteration":311,"passed_time":0.1880252532,"remaining_time":0.4146197891},
{"learn":[4.402139942],"iteration":312,"passed_time":0.1887395349,"remaining_time":0.4142621741},
{"learn":[4.400284725],"iteration":313,"passed_time":0.1892595127,"remaining_time":0.4134777889},
{"learn":[4.395805521],"iteration":314,"passed_time":0.1897865388,"remaining_time":0.4127104098},
{"learn":[4.392838833],"iteration":315,"passed_time":0.1902589266,"remaining_time":0.4118262841},
{"learn":[4.389213061],"iteration":316,"passed_time":0.1908548564,"remaining_time":0.4112109366},
{"learn":[4.3861981],"iteration":317,"passed_time":0.1916738737,"remaining_time":0.4110741569},
{"learn":[4.385054234],"iteration":318,"passed_time":0.1922351075,"remaining_time":0.4103827844},
{"learn":[4.379364607],"iteration":319,"passed_time":0.1928387618,"remaining_time":0.4097823687},
{"learn":[4.378387619],"iteration":320,"passed_time":0.1935386943,"remaining_time":0.4093855871},
{"learn":[4.375816727],"iteration":321,"passed_time":0.1941393726,"remaining_time":0.4087779335},
{"learn":[4.374600202],"iteration":322,"passed_time":0.1946762243,"remaining_time":0.4080365444},
{"learn":[4.37098897],"iteration":323,"passed_time":0.1953133543,"remaining_time":0.4075056406},
{"learn":[4.367418484],"iteration":324,"passed_time":0.1959781527,"remaining_time":0.4070315479},
{"learn":[4.363584638],"iteration":325,"passed_time":0.1965293877,"remaining_time":0.4063214948},
{"learn":[4.360770706],"iteration":326,"passed_time":0.1970688561,"remaining_time":0.4055881961},
{"learn":[4.358675808],"iteration":327,"passed_time":0.1976582776,"remaining_time":0.4049584225},
{"learn":[4.354228195],"iteration":328,"passed_time":0.1982548866,"remaining_time":0.4043435528},
{"learn":[4.353773425],"iteration":329,"passed_time":0.1987476137,"remaining_time":0.4035178823},
{"learn":[4.351648009],"iteration":330,"passed_time":0.199265911,"remaining_time":0.4027459046},
{"learn":[4.348209927],"iteration":331,"passed_time":0.1997461466,"remaining_time":0.4018988734},
{"learn":[4.345852733],"iteration":332,"passed_time":0.2002272582,"remaining_time":0.4010557995},
{"learn":[4.34237339],"iteration":333,"passed_time":0.2011648303,"remaining_time":0.4011250808},
{"learn":[4.340814362],"iteration":334,"passed_time":0.2017981887,"remaining_time":0.4005844642},
{"learn":[4.339707068],"iteration":335,"passed_time":0.2025668699,"remaining_time":0.4003107191},
{"learn":[4.335430786],"iteration":336,"passed_time":0.2036184064,"remaining_time":0.4005905147},
{"learn":[4.33521887],"iteration":337,"passed_time":0.2041386598,"remaining_time":0.3998218721},
{"learn":[4.328507238],"iteration":338,"passed_time":0.2047673526,"remaining_time":0.3992661359},
{"learn":[4.326140732],"iteration":339,"passed_time":0.2054558217,"remaining_time":0.3988260069},
{"learn":[4.323785636],"iteration":340,"passed_time":0.2060580239,"remaining_time":0.3982177059},
{"learn":[4.320632534],"iteration":341,"passed_time":0.206816114,"remaining_time":0.3979093655},
{"learn":[4.31973724],"iteration":342,"passed_time":0.2073478313,"remaining_time":0.3971647964},
{"learn":[4.318000924],"iteration":343,"passed_time":0.2078999788,"remaining_time":0.3964604247},
{"learn":[4.312713628],"iteration":344,"passed_time":0.2085106518,"remaining_time":0.395868049},
{"learn":[4.308220789],"iteration":345,"passed_time":0.209081919,"remaining_time":0.3952010838},
{"learn":[4.305890947],"iteration":346,"passed_time":0.2096035552,"remaining_time":0.3944412724},
{"learn":[4.305137856],"iteration":347,"passed_time":0.2111224072,"remaining_time":0.3955511768},
{"learn":[4.304787172],"iteration":348,"passed_time":0.2116114932,"remaining_time":0.3947251636},
{"learn":[4.30350134],"iteration":349,"passed_time":0.2120672806,"remaining_time":0.3938392355},
{"learn":[4.30293809],"iteration":350,"passed_time":0.2125572541,"remaining_time":0.3930189684},
{"learn":[4.299548459],"iteration":351,"passed_time":0.2130514594,"remaining_time":0.3922083685},
{"learn":[4.294768408],"iteration":352,"passed_time":0.2135663364,"remaining_time":0.3914374495},
{"learn":[4.294581479],"iteration":353,"passed_time":0.2140482536,"remaining_time":0.3906078301},
{"learn":[4.292551604],"iteration":354,"passed_time":0.2145024308,"remaining_time":0.3897297686},
{"learn":[4.288628894],"iteration":355,"passed_time":0.215008079,"remaining_time":0.3889471991},
{"learn":[4.287802767],"iteration":356,"passed_time":0.2154938963,"remaining_time":0.3881304631},
{"learn":[4.284566905],"iteration":357,"passed_time":0.2160901875,"remaining_time":0.3875136883},
{"learn":[4.27890232],"iteration":358,"passed_time":0.2170271392,"remaining_time":0.387505282},
{"learn":[4.276938023],"iteration":359,"passed_time":0.2178272869,"remaining_time":0.38724851},
{"learn":[4.273425094],"iteration":360,"passed_time":0.2184171647,"remaining_time":0.3866165326},
{"learn":[4.269726505],"iteration":361,"passed_time":0.2190192007,"remaining_time":0.3860062156},
{"learn":[4.265565857],"iteration":362,"passed_time":0.2195826375,"remaining_time":0.3853282096},
{"learn":[4.262117173],"iteration":363,"passed_time":0.2202047157,"remaining_time":0.3847532945},
{"learn":[4.259185148],"iteration":364,"passed_time":0.2207860906,"remaining_time":0.3841073083},
{"learn":[4.257668507],"iteration":365,"passed_time":0.2213179369,"remaining_time":0.3833758797},
{"learn":[4.253432436],"iteration":366,"passed_time":0.2218591641,"remaining_time":0.382661719},
{"learn":[4.250216667],"iteration":367,"passed_time":0.2224194953,"remaining_time":0.3819813072},
{"learn":[4.24514828],"iteration":368,"passed_time":0.2231318295,"remaining_time":0.3815614754},
{"learn":[4.244015772],"iteration":369,"passed_time":0.2236757617,"remaining_time":0.380853324},
{"learn":[4.240329192],"iteration":370,"passed_time":0.2242047309,"remaining_time":0.3801206892},
{"learn":[4.236718014],"iteration":371,"passed_time":0.224702113,"remaining_time":0.3793358252},
{"learn":[4.233495944],"iteration":372,"passed_time":0.2251673285,"remaining_time":0.3784984315},
{"learn":[4.230357491],"iteration":373,"passed_time":0.2256320404,"remaining_time":0.3776621854},
{"learn":[4.227381215],"iteration":374,"passed_time":0.2261316237,"remaining_time":0.3768860394},
{"learn":[4.226169067],"iteration":375,"passed_time":0.2266398042,"remaining_time":0.3761256325},
{"learn":[4.225963861],"iteration":376,"passed_time":0.2271206322,"remaining_time":0.375321363},
{"learn":[4.224346548],"iteration":377,"passed_time":0.2276480257,"remaining_time":0.3745954286},
{"learn":[4.222595381],"iteration":378,"passed_time":0.2281216066,"remaining_time":0.3737823686},
{"learn":[4.219700938],"iteration":379,"passed_time":0.2286007174,"remaining_time":0.3729801179},
{"learn":[4.216356207],"iteration":380,"passed_time":0.2290800089,"remaining_time":0.3721798571},
{"learn":[4.214326494],"iteration":381,"passed_time":0.2297856632,"remaining_time":0.3717474866},
{"learn":[4.212901398],"iteration":382,"passed_time":0.2301619127,"remaining_time":0.3707830291},
{"learn":[4.211331091],"iteration":383,"passed_time":0.2307695263,"remaining_time":0.3701927818},
{"learn":[4.208624791],"iteration":384,"passed_time":0.2320817431,"remaining_time":0.3707279792},
{"learn":[4.204659106],"iteration":385,"passed_time":0.2327418116,"remaining_time":0.3702162496},
{"learn":[4.202968852],"iteration":386,"passed_time":0.2332766535,"remaining_time":0.369505397},
{"learn":[4.197261935],"iteration":387,"passed_time":0.2339874819,"remaining_time":0.3690730384},
{"learn":[4.196934403],"iteration":388,"passed_time":0.2347226913,"remaining_time":0.3686775434},
{"learn":[4.192479929],"iteration":389,"passed_time":0.2353794459,"remaining_time":0.3681575949},
{"learn":[4.190243116],"iteration":390,"passed_time":0.2360404671,"remaining_time":0.367643592},
{"learn":[4.185852431],"iteration":391,"passed_time":0.236766004,"remaining_time":0.3672289042},
{"learn":[4.180967944],"iteration":392,"passed_time":0.2373030184,"remaining_time":0.3665214558},
{"learn":[4.178283162],"iteration":393,"passed_time":0.2378664461,"remaining_time":0.3658554984},
{"learn":[4.176341157],"iteration":394,"passed_time":0.2384337324,"remaining_time":0.3651959698},
{"learn":[4.176041504],"iteration":395,"passed_time":0.2388918041,"remaining_time":0.3643703275},
{"learn":[4.175564513],"iteration":396,"passed_time":0.2394044655,"remaining_time":0.3636294527},
{"learn":[4.170830274],"iteration":397,"passed_time":0.2398777347,"remaining_time":0.3628301414},
{"learn":[4.167804808],"iteration":398,"passed_time":0.2411660644,"remaining_time":0.3632601621},
{"learn":[4.165860548],"iteration":399,"passed_time":0.2418162591,"remaining_time":0.3627243887},
{"learn":[4.160950571],"iteration":400,"passed_time":0.2423104494,"remaining_time":0.3619550104},
{"learn":[4.158544115],"iteration":401,"passed_time":0.2427844077,"remaining_time":0.361156905},
{"learn":[4.154448767],"iteration":402,"passed_time":0.2433451195,"remaining_time":0.3604889239},
{"learn":[4.15197457],"iteration":403,"passed_time":0.2438737769,"remaining_time":0.3597741858},
{"learn":[4.149562679],"iteration":404,"passed_time":0.2444036345,"remaining_time":0.3590621297},
{"learn":[4.149327961],"iteration":405,"passed_time":0.2448760544,"remaining_time":0.3582669367},
{"learn":[4.147444889],"iteration":406,"passed_time":0.2455077228,"remaining_time":0.3577053553},
{"learn":[4.147254809],"iteration":407,"passed_time":0.2463159071,"remaining_time":0.3573995515},
{"learn":[4.144589165],"iteration":408,"passed_time":0.2468967464,"remaining_time":0.3567627803},
{"learn":[4.141691034],"iteration":409,"passed_time":0.2474570129,"remaining_time":0.3560966772},
{"learn":[4.138893468],"iteration":410,"passed_time":0.2480055826,"remaining_time":0.3554143264},
{"learn":[4.136964597],"iteration":411,"passed_time":0.2485538049,"remaining_time":0.3547321293},
{"learn":[4.133773523],"iteration":412,"passed_time":0.2491022275,"remaining_time":0.3540508657},
{"learn":[4.131363444],"iteration":413,"passed_time":0.2496968648,"remaining_time":0.3534356589},
{"learn":[4.130228592],"iteration":414,"passed_time":0.2502129415,"remaining_time":0.352709809},
{"learn":[4.12884186],"iteration":415,"passed_time":0.2508466563,"remaining_time":0.3521501136},
{"learn":[4.12413494],"iteration":416,"passed_time":0.2515168149,"remaining_time":0.3516410146},
{"learn":[4.119422508],"iteration":417,"passed_time":0.2520757483,"remaining_time":0.3509762811},
{"learn":[4.117038244],"iteration":418,"passed_time":0.2526334975,"remaining_time":0.3503104106},
{"learn":[4.116067631],"iteration":419,"passed_time":0.253116764,"remaining_time":0.3495421978},
{"learn":[4.110343455],"iteration":420,"passed_time":0.2536985399,"remaining_time":0.3489108185},
{"learn":[4.105604544],"iteration":421,"passed_time":0.254269924,"remaining_time":0.3482654409},
{"learn":[4.103390131],"iteration":422,"passed_time":0.2548229615,"remaining_time":0.3475953872},
{"learn":[4.096724402],"iteration":423,"passed_time":0.25534274,"remaining_time":0.3468807034},
{"learn":[4.093431279],"iteration":424,"passed_time":0.2559997938,"remaining_time":0.3463526622},
{"learn":[4.091412744],"iteration":425,"passed_time":0.2565819,"remaining_time":0.3457230296},
{"learn":[4.091192901],"iteration":426,"passed_time":0.2571559635,"remaining_time":0.3450828269},
{"learn":[4.088994581],"iteration":427,"passed_time":0.2578114247,"remaining_time":0.3445517171},
{"learn":[4.087845355],"iteration":428,"passed_time":0.2583632861,"remaining_time":0.343882136},
{"learn":[4.083650279],"iteration":429,"passed_time":0.2589070853,"remaining_time":0.3432024153},
{"learn":[4.079840652],"iteration":430,"passed_time":0.2594446939,"remaining_time":0.3425151528},
{"learn":[4.075707828],"iteration":431,"passed_time":0.2599308049,"remaining_time":0.3417608731},
{"learn":[4.071345409],"iteration":432,"passed_time":0.260440302,"remaining_time":0.3410384555},
{"learn":[4.067460475],"iteration":433,"passed_time":0.2609976829,"remaining_time":0.3403794666},
{"learn":[4.064914749],"iteration":434,"passed_time":0.2615021003,"remaining_time":0.3396521533},
{"learn":[4.063823175],"iteration":435,"passed_time":0.2620275533,"remaining_time":0.3389530736},
{"learn":[4.058898471],"iteration":436,"passed_time":0.2626552578,"remaining_time":0.3383865221},
{"learn":[4.054120355],"iteration":437,"passed_time":0.2632850118,"remaining_time":0.3378223211},
{"learn":[4.052715901],"iteration":438,"passed_time":0.2640646003,"remaining_time":0.3374492956},
{"learn":[4.052114167],"iteration":439,"passed_time":0.2648336042,"remaining_time":0.3370609508},
{"learn":[4.051377267],"iteration":440,"passed_time":0.2653969712,"remaining_time":0.3364102198},
{"learn":[4.049275336],"iteration":441,"passed_time":0.2659155355,"remaining_time":0.3357033232},
{"learn":[4.047099198],"iteration":442,"passed_time":0.2665845186,"remaining_time":0.3351864038},
{"learn":[4.044348685],"iteration":443,"passed_time":0.2672015422,"remaining_time":0.3346037331},
{"learn":[4.042822379],"iteration":444,"passed_time":0.2677845042,"remaining_time":0.3339784266},
{"learn":[4.041258611],"iteration":445,"passed_time":0.2683832224,"remaining_time":0.3333728816},
{"learn":[4.040044254],"iteration":446,"passed_time":0.2689343499,"remaining_time":0.3327084911},
{"learn":[4.036860137],"iteration":447,"passed_time":0.2694568711,"remaining_time":0.332009359},
{"learn":[4.036372284],"iteration":448,"passed_time":0.2700255362,"remaining_time":0.3313676402},
{"learn":[4.03368231],"iteration":449,"passed_time":0.2705637411,"remaining_time":0.3306890169},
{"learn":[4.032439519],"iteration":450,"passed_time":0.2711540622,"remaining_time":0.3300744571},
{"learn":[4.032008634],"iteration":451,"passed_time":0.2716739913,"remaining_time":0.329374662},
{"learn":[4.030034932],"iteration":452,"passed_time":0.2721686449,"remaining_time":0.3286451407},
{"learn":[4.028173412],"iteration":453,"passed_time":0.2726621435,"remaining_time":0.3279152651},
{"learn":[4.023806097],"iteration":454,"passed_time":0.2731658075,"remaining_time":0.3271986046},
{"learn":[4.020239186],"iteration":455,"passed_time":0.2737202329,"remaining_time":0.3265434357},
{"learn":[4.017384838],"iteration":456,"passed_time":0.2745602994,"remaining_time":0.3262281019},
{"learn":[4.016468229],"iteration":457,"passed_time":0.2754871489,"remaining_time":0.3260131762},
{"learn":[4.014530169],"iteration":458,"passed_time":0.2760098507,"remaining_time":0.3253188001},
{"learn":[4.012884822],"iteration":459,"passed_time":0.276591476,"remaining_time":0.3246943414},
{"learn":[4.008924707],"iteration":460,"passed_time":0.2772860082,"remaining_time":0.324202079},
{"learn":[4.008286778],"iteration":461,"passed_time":0.2778468063,"remaining_time":0.3235532073},
{"learn":[4.006444202],"iteration":462,"passed_time":0.2785138659,"remaining_time":0.3230279611},
{"learn":[4.003284363],"iteration":463,"passed_time":0.2791389277,"remaining_time":0.3224535889},
{"learn":[3.999811484],"iteration":464,"passed_time":0.2797496443,"remaining_time":0.321862494},
{"learn":[3.997483319],"iteration":465,"passed_time":0.2803428772,"remaining_time":0.3212512798},
{"learn":[3.99708333],"iteration":466,"passed_time":0.2808802012,"remaining_time":0.3205763324},
{"learn":[3.995860263],"iteration":467,"passed_time":0.2814247939,"remaining_time":0.3199102358},
{"learn":[3.994131111],"iteration":468,"passed_time":0.2819365654,"remaining_time":0.3192074973},
{"learn":[3.993125499],"iteration":469,"passed_time":0.2824722009,"remaining_time":0.3185324819},
{"learn":[3.992954084],"iteration":470,"passed_time":0.2829637138,"remaining_time":0.3178085024},
{"learn":[3.990635743],"iteration":471,"passed_time":0.2834925414,"remaining_time":0.3171272497},
{"learn":[3.986678254],"iteration":472,"passed_time":0.2840177605,"remaining_time":0.3164426212},
{"learn":[3.986393291],"iteration":473,"passed_time":0.2846067329,"remaining_time":0.3158294124},
{"learn":[3.986152671],"iteration":474,"passed_time":0.2851881228,"remaining_time":0.3152079252},
{"learn":[3.985596662],"iteration":475,"passed_time":0.2857214117,"remaining_time":0.3145336549},
{"learn":[3.983853457],"iteration":476,"passed_time":0.2862221775,"remaining_time":0.3138243162},
{"learn":[3.983263928],"iteration":477,"passed_time":0.2867394463,"remaining_time":0.3131338723},
{"learn":[3.980067202],"iteration":478,"passed_time":0.2872770655,"remaining_time":0.3124662862},
{"learn":[3.978115407],"iteration":479,"passed_time":0.287837198,"remaining_time":0.3118236311},
{"learn":[3.972661644],"iteration":480,"passed_time":0.2886672456,"remaining_time":0.3114725581},
{"learn":[3.969938254],"iteration":481,"passed_time":0.2896980823,"remaining_time":0.3113352835},
{"learn":[3.968211434],"iteration":482,"passed_time":0.2902521608,"remaining_time":0.31068399},
{"learn":[3.966113368],"iteration":483,"passed_time":0.2907678661,"remaining_time":0.3099921878},
{"learn":[3.962246044],"iteration":484,"passed_time":0.2913458327,"remaining_time":0.3093672244},
{"learn":[3.961319703],"iteration":485,"passed_time":0.2920468003,"remaining_time":0.3088725419},
{"learn":[3.96078191],"iteration":486,"passed_time":0.2926706157,"remaining_time":0.308295741},
{"learn":[3.958913633],"iteration":487,"passed_time":0.2932085783,"remaining_time":0.3076286723},
{"learn":[3.957428286],"iteration":488,"passed_time":0.2937423074,"remaining_time":0.3069577077},
{"learn":[3.952641965],"iteration":489,"passed_time":0.2943144208,"remaining_time":0.3063272543},
{"learn":[3.951486786],"iteration":490,"passed_time":0.294837068,"remaining_time":0.3056457589},
{"learn":[3.94938344],"iteration":491,"passed_time":0.2954938432,"remaining_time":0.3051033991},
{"learn":[3.947297924],"iteration":492,"passed_time":0.2960120185,"remaining_time":0.3044180393},
{"learn":[3.946284886],"iteration":493,"passed_time":0.2965320836,"remaining_time":0.3037352922},
{"learn":[3.943288204],"iteration":494,"passed_time":0.2970166647,"remaining_time":0.3030170013},
{"learn":[3.943076488],"iteration":495,"passed_time":0.2974970429,"remaining_time":0.3022953823},
{"learn":[3.942347078],"iteration":496,"passed_time":0.297952492,"remaining_time":0.301549504},
{"learn":[3.940251541],"iteration":497,"passed_time":0.2984249289,"remaining_time":0.3008219163},
{"learn":[3.939011019],"iteration":498,"passed_time":0.298942536,"remaining_time":0.3001407025},
{"learn":[3.938760512],"iteration":499,"passed_time":0.2994024569,"remaining_time":0.2994024569},
{"learn":[3.934522727],"iteration":500,"passed_time":0.2998884695,"remaining_time":0.29869131},
{"learn":[3.930091193],"iteration":501,"passed_time":0.3003395251,"remaining_time":0.2979463814},
{"learn":[3.927671752],"iteration":502,"passed_time":0.3008132239,"remaining_time":0.2972249946},
{"learn":[3.927280041],"iteration":503,"passed_time":0.3012947265,"remaining_time":0.2965122705},
{"learn":[3.925987561],"iteration":504,"passed_time":0.3022098766,"remaining_time":0.2962255226},
{"learn":[3.921645957],"iteration":505,"passed_time":0.3028182979,"remaining_time":0.2956368362},
{"learn":[3.920333743],"iteration":506,"passed_time":0.3036645001,"remaining_time":0.2952792871},
{"learn":[3.918659461],"iteration":507,"passed_time":0.3044648511,"remaining_time":0.294875407},
{"learn":[3.916124385],"iteration":508,"passed_time":0.3050787215,"remaining_time":0.294290083},
{"learn":[3.913849268],"iteration":509,"passed_time":0.3056414591,"remaining_time":0.2936555195},
{"learn":[3.912826119],"iteration":510,"passed_time":0.3063124986,"remaining_time":0.2931248764},
{"learn":[3.910034145],"iteration":511,"passed_time":0.3068703437,"remaining_time":0.2924857964},
{"learn":[3.90792379],"iteration":512,"passed_time":0.3076239424,"remaining_time":0.2920328654},
{"learn":[3.907823851],"iteration":513,"passed_time":0.3082023132,"remaining_time":0.2914130821},
{"learn":[3.904527401],"iteration":514,"passed_time":0.3087634761,"remaining_time":0.2907772542},
{"learn":[3.903378283],"iteration":515,"passed_time":0.3093389878,"remaining_time":0.2901551746},
{"learn":[3.902170135],"iteration":516,"passed_time":0.3098397004,"remaining_time":0.2894633951},
{"learn":[3.899435429],"iteration":517,"passed_time":0.3103661031,"remaining_time":0.2887962581},
{"learn":[3.897497505],"iteration":518,"passed_time":0.3108729188,"remaining_time":0.2881115105},
{"learn":[3.896426119],"iteration":519,"passed_time":0.3114370749,"remaining_time":0.2874803768},
{"learn":[3.896044669],"iteration":520,"passed_time":0.3119102005,"remaining_time":0.2867658082},
{"learn":[3.892795942],"iteration":521,"passed_time":0.3123743333,"remaining_time":0.2860439297},
{"learn":[3.892413888],"iteration":522,"passed_time":0.312848126,"remaining_time":0.2853318472},
{"learn":[3.891738985],"iteration":523,"passed_time":0.3132975612,"remaining_time":0.284598548},
{"learn":[3.88822057],"iteration":524,"passed_time":0.3137968392,"remaining_time":0.283911426},
{"learn":[3.883837053],"iteration":525,"passed_time":0.3142832609,"remaining_time":0.2832134328},
{"learn":[3.881769742],"iteration":526,"passed_time":0.3147630057,"remaining_time":0.2825102499},
{"learn":[3.880356898],"iteration":527,"passed_time":0.3153024851,"remaining_time":0.2818613124},
{"learn":[3.879250273],"iteration":528,"passed_time":0.3158071751,"remaining_time":0.2811818138},
{"learn":[3.877174493],"iteration":529,"passed_time":0.3162635277,"remaining_time":0.2804601095},
{"learn":[3.875854201],"iteration":530,"passed_time":0.3167769837,"remaining_time":0.2797898406},
{"learn":[3.873189396],"iteration":531,"passed_time":0.3173428519,"remaining_time":0.2791662682},
{"learn":[3.871583368],"iteration":532,"passed_time":0.318755854,"remaining_time":0.2792851479},
{"learn":[3.869622679],"iteration":533,"passed_time":0.3193281748,"remaining_time":0.2786646619},
{"learn":[3.866860164],"iteration":534,"passed_time":0.3198980581,"remaining_time":0.2780422374},
{"learn":[3.864498444],"iteration":535,"passed_time":0.3205020522,"remaining_time":0.2774495377},
{"learn":[3.861416322],"iteration":536,"passed_time":0.3210295039,"remaining_time":0.2767908014},
{"learn":[3.860265769],"iteration":537,"passed_time":0.3215712667,"remaining_time":0.2761448424},
{"learn":[3.859328725],"iteration":538,"passed_time":0.3222152333,"remaining_time":0.2755866838},
{"learn":[3.858521278],"iteration":539,"passed_time":0.3228326484,"remaining_time":0.2750055894},
{"learn":[3.85599111],"iteration":540,"passed_time":0.3234638595,"remaining_time":0.2744360656},
{"learn":[3.852379816],"iteration":541,"passed_time":0.3240093422,"remaining_time":0.2737938722},
{"learn":[3.851327537],"iteration":542,"passed_time":0.3245301914,"remaining_time":0.2731313029},
{"learn":[3.847854898],"iteration":543,"passed_time":0.3250245006,"remaining_time":0.2724470079},
{"learn":[3.847083414],"iteration":544,"passed_time":0.3254777175,"remaining_time":0.2717291036},
{"learn":[3.845397429],"iteration":545,"passed_time":0.3259695432,"remaining_time":0.2710442722},
{"learn":[3.841933528],"iteration":546,"passed_time":0.3264801968,"remaining_time":0.2703757388},
{"learn":[3.840996474],"iteration":547,"passed_time":0.3270103049,"remaining_time":0.2697238281},
{"learn":[3.838355966],"iteration":548,"passed_time":0.3274949607,"remaining_time":0.2690350224},
{"learn":[3.83342799],"iteration":549,"passed_time":0.327986327,"remaining_time":0.2683524494},
{"learn":[3.828161535],"iteration":550,"passed_time":0.3284614539,"remaining_time":0.2676573372},
{"learn":[3.823502399],"iteration":551,"passed_time":0.3289295937,"remaining_time":0.2669573514},
{"learn":[3.820068862],"iteration":552,"passed_time":0.3297333198,"remaining_time":0.2665294646},
{"learn":[3.817951642],"iteration":553,"passed_time":0.3302647756,"remaining_time":0.2658810287},
{"learn":[3.815785958],"iteration":554,"passed_time":0.3307293871,"remaining_time":0.2651794185},
{"learn":[3.81503012],"iteration":555,"passed_time":0.331243193,"remaining_time":0.2645179455},
{"learn":[3.813529315],"iteration":556,"passed_time":0.3319045806,"remaining_time":0.2639743792},
{"learn":[3.808881326],"iteration":557,"passed_time":0.3331379015,"remaining_time":0.2638834274},
{"learn":[3.808740434],"iteration":558,"passed_time":0.3337606684,"remaining_time":0.2633067169},
{"learn":[3.80714352],"iteration":559,"passed_time":0.3342860998,"remaining_time":0.2626533641},
{"learn":[3.80573346],"iteration":560,"passed_time":0.3348260621,"remaining_time":0.2620118383},
{"learn":[3.803370052],"iteration":561,"passed_time":0.3353606736,"remaining_time":0.2613665037},
{"learn":[3.803215211],"iteration":562,"passed_time":0.3359759901,"remaining_time":0.2607842055},
{"learn":[3.801309667],"iteration":563,"passed_time":0.3365516127,"remaining_time":0.2601711048},
{"learn":[3.800003847],"iteration":564,"passed_time":0.3370972249,"remaining_time":0.2595350315},
{"learn":[3.798026138],"iteration":565,"passed_time":0.3376607626,"remaining_time":0.2589130229},
{"learn":[3.794745847],"iteration":566,"passed_time":0.3384529469,"remaining_time":0.2584658307},
{"learn":[3.794312041],"iteration":567,"passed_time":0.3390256607,"remaining_time":0.2578505025},
{"learn":[3.792205926],"iteration":568,"passed_time":0.3395736957,"remaining_time":0.2572166307},
{"learn":[3.788991061],"iteration":569,"passed_time":0.3401211998,"remaining_time":0.2565826595},
{"learn":[3.787391572],"iteration":570,"passed_time":0.3406633656,"remaining_time":0.2559449805},
{"learn":[3.7826445],"iteration":571,"passed_time":0.3411513584,"remaining_time":0.2552671003},
{"learn":[3.781700331],"iteration":572,"passed_time":0.3416350509,"remaining_time":0.2545866785},
{"learn":[3.780045374],"iteration":573,"passed_time":0.342122484,"remaining_time":0.2539097181},
{"learn":[3.775462644],"iteration":574,"passed_time":0.342603171,"remaining_time":0.2532284307},
{"learn":[3.773711943],"iteration":575,"passed_time":0.3431317381,"remaining_time":0.252583085},
{"learn":[3.772415806],"iteration":576,"passed_time":0.3436289676,"remaining_time":0.2519151704},
{"learn":[3.770170875],"iteration":577,"passed_time":0.3441059347,"remaining_time":0.2512330526},
{"learn":[3.765166479],"iteration":578,"passed_time":0.3446092092,"remaining_time":0.2505707721},
{"learn":[3.763976102],"iteration":579,"passed_time":0.3450731908,"remaining_time":0.2498805865},
{"learn":[3.760761708],"iteration":580,"passed_time":0.3456063713,"remaining_time":0.2492410836},
{"learn":[3.758155662],"iteration":581,"passed_time":0.3461163177,"remaining_time":0.2485852591},
{"learn":[3.756844548],"iteration":582,"passed_time":0.3469500039,"remaining_time":0.2481614951},
{"learn":[3.753098923],"iteration":583,"passed_time":0.3476754249,"remaining_time":0.2476592068},
{"learn":[3.751618946],"iteration":584,"passed_time":0.3482374562,"remaining_time":0.2470402467},
{"learn":[3.751398464],"iteration":585,"passed_time":0.3487481535,"remaining_time":0.2463852143},
{"learn":[3.749920103],"iteration":586,"passed_time":0.3493675644,"remaining_time":0.245807162},
{"learn":[3.748237465],"iteration":587,"passed_time":0.3500784645,"remaining_time":0.2452930738},
{"learn":[3.746021536],"iteration":588,"passed_time":0.3506894647,"remaining_time":0.2447086078},
{"learn":[3.74417648],"iteration":589,"passed_time":0.3514362857,"remaining_time":0.2442184358},
{"learn":[3.738788389],"iteration":590,"passed_time":0.3519643759,"remaining_time":0.2435760233},
{"learn":[3.736021611],"iteration":591,"passed_time":0.3525076224,"remaining_time":0.2429444425},
{"learn":[3.734546151],"iteration":592,"passed_time":0.3530944203,"remaining_time":0.2423430507},
{"learn":[3.733527479],"iteration":593,"passed_time":0.3536538415,"remaining_time":0.2417229961},
{"learn":[3.733026392],"iteration":594,"passed_time":0.3541709437,"remaining_time":0.2410743398},
{"learn":[3.730314752],"iteration":595,"passed_time":0.3547044007,"remaining_time":0.2404372112},
{"learn":[3.727342596],"iteration":596,"passed_time":0.3551922575,"remaining_time":0.2397696478},
{"learn":[3.725459604],"iteration":597,"passed_time":0.3556864287,"remaining_time":0.2391069303},
{"learn":[3.723158842],"iteration":598,"passed_time":0.3561940757,"remaining_time":0.2384537969},
{"learn":[3.722362756],"iteration":599,"passed_time":0.3567182106,"remaining_time":0.2378121404},
{"learn":[3.721443615],"iteration":600,"passed_time":0.3572308996,"remaining_time":0.2371632761},
{"learn":[3.720743486],"iteration":601,"passed_time":0.3577392689,"remaining_time":0.2365120083},
{"learn":[3.720215334],"iteration":602,"passed_time":0.3582528579,"remaining_time":0.2358646511},
{"learn":[3.719436563],"iteration":603,"passed_time":0.3587071319,"remaining_time":0.2351788481},
{"learn":[3.715046574],"iteration":604,"passed_time":0.3591992361,"remaining_time":0.2345185095},
{"learn":[3.71443396],"iteration":605,"passed_time":0.3600908696,"remaining_time":0.2341184861},
{"learn":[3.712938941],"iteration":606,"passed_time":0.3606564517,"remaining_time":0.2335057422},
{"learn":[3.712814764],"iteration":607,"passed_time":0.3615956049,"remaining_time":0.2331340084},
{"learn":[3.71235348],"iteration":608,"passed_time":0.3621731032,"remaining_time":0.2325282157},
{"learn":[3.711223749],"iteration":609,"passed_time":0.3626747886,"remaining_time":0.2318740452},
{"learn":[3.710755648],"iteration":610,"passed_time":0.3631340228,"remaining_time":0.2311933468},
{"learn":[3.708668039],"iteration":611,"passed_time":0.3636264879,"remaining_time":0.2305344401},
{"learn":[3.705623591],"iteration":612,"passed_time":0.3649394923,"remaining_time":0.2303941004},
{"learn":[3.704045802],"iteration":613,"passed_time":0.3654761784,"remaining_time":0.2297618972},
{"learn":[3.699915209],"iteration":614,"passed_time":0.3660348557,"remaining_time":0.2291437715},
{"learn":[3.696182221],"iteration":615,"passed_time":0.3666114997,"remaining_time":0.2285370388},
{"learn":[3.694263278],"iteration":616,"passed_time":0.3671856345,"remaining_time":0.2279288461},
{"learn":[3.693810229],"iteration":617,"passed_time":0.3677750872,"remaining_time":0.2273302319},
{"learn":[3.690900932],"iteration":618,"passed_time":0.3682685944,"remaining_time":0.226672592},
{"learn":[3.688020895],"iteration":619,"passed_time":0.3687901036,"remaining_time":0.2260326441},
{"learn":[3.685491894],"iteration":620,"passed_time":0.3693552947,"remaining_time":0.225419737},
{"learn":[3.684328128],"iteration":621,"passed_time":0.3699561526,"remaining_time":0.2248286587},
{"learn":[3.680640153],"iteration":622,"passed_time":0.3704766364,"remaining_time":0.2241889116},
{"learn":[3.678932783],"iteration":623,"passed_time":0.3710239582,"remaining_time":0.2235657184},
{"learn":[3.674167041],"iteration":624,"passed_time":0.3715639315,"remaining_time":0.2229383589},
{"learn":[3.672200976],"iteration":625,"passed_time":0.3721418665,"remaining_time":0.2223339586},
{"learn":[3.670606604],"iteration":626,"passed_time":0.3726404213,"remaining_time":0.2216824197},
{"learn":[3.665506042],"iteration":627,"passed_time":0.373109593,"remaining_time":0.2210139628},
{"learn":[3.664214007],"iteration":628,"passed_time":0.3735617539,"remaining_time":0.220336106},
{"learn":[3.66261643],"iteration":629,"passed_time":0.3740432404,"remaining_time":0.2196761888},
{"learn":[3.662118449],"iteration":630,"passed_time":0.3745804721,"remaining_time":0.2190494361},
{"learn":[3.660871366],"iteration":631,"passed_time":0.3750689507,"remaining_time":0.2183945789},
{"learn":[3.656695243],"iteration":632,"passed_time":0.3757181983,"remaining_time":0.2178334578},
{"learn":[3.654497801],"iteration":633,"passed_time":0.3767072565,"remaining_time":0.2174682269},
{"learn":[3.654189134],"iteration":634,"passed_time":0.3772909152,"remaining_time":0.2168680064},
{"learn":[3.653957699],"iteration":635,"passed_time":0.3778305522,"remaining_time":0.2162426431},
{"learn":[3.651920725],"iteration":636,"passed_time":0.3784036515,"remaining_time":0.2156366177},
{"learn":[3.65106705],"iteration":637,"passed_time":0.3790502794,"remaining_time":0.2150724156},
{"learn":[3.650612844],"iteration":638,"passed_time":0.3796305801,"remaining_time":0.2144704842},
{"learn":[3.649884732],"iteration":639,"passed_time":0.3802484871,"remaining_time":0.213889774},
{"learn":[3.646276182],"iteration":640,"passed_time":0.3808550276,"remaining_time":0.2133025818},
{"learn":[3.645808194],"iteration":641,"passed_time":0.381448919,"remaining_time":0.2127082757},
{"learn":[3.645042989],"iteration":642,"passed_time":0.3820041128,"remaining_time":0.2120924857},
{"learn":[3.639864499],"iteration":643,"passed_time":0.3826080763,"remaining_time":0.2115038434},
{"learn":[3.637318478],"iteration":644,"passed_time":0.3831282664,"remaining_time":0.2108690458},
{"learn":[3.636344905],"iteration":645,"passed_time":0.3836574388,"remaining_time":0.2102395253},
{"learn":[3.634754643],"iteration":646,"passed_time":0.3841450376,"remaining_time":0.2095876326},
{"learn":[3.630724975],"iteration":647,"passed_time":0.3846353769,"remaining_time":0.2089377356},
{"learn":[3.629408252],"iteration":648,"passed_time":0.3851105128,"remaining_time":0.2082801079},
{"learn":[3.62790646],"iteration":649,"passed_time":0.3856150814,"remaining_time":0.20763889},
{"learn":[3.627388973],"iteration":650,"passed_time":0.3861464398,"remaining_time":0.2070124539},
{"learn":[3.625163557],"iteration":651,"passed_time":0.3866143397,"remaining_time":0.206352439},
{"learn":[3.623701985],"iteration":652,"passed_time":0.3870848265,"remaining_time":0.2056943871},
{"learn":[3.622342639],"iteration":653,"passed_time":0.3875520312,"remaining_time":0.2050351725},
{"learn":[3.621130639],"iteration":654,"passed_time":0.3880762615,"remaining_time":0.2044065805},
{"learn":[3.619125665],"iteration":655,"passed_time":0.3885847894,"remaining_time":0.2037700725},
{"learn":[3.618878783],"iteration":656,"passed_time":0.3891196544,"remaining_time":0.2031477039},
{"learn":[3.616207429],"iteration":657,"passed_time":0.3896329166,"remaining_time":0.2025143731},
{"learn":[3.61206486],"iteration":658,"passed_time":0.3903095509,"remaining_time":0.2019659436},
{"learn":[3.611955873],"iteration":659,"passed_time":0.3913334522,"remaining_time":0.2015960208},
{"learn":[3.610713743],"iteration":660,"passed_time":0.392037168,"remaining_time":0.2010599091},
{"learn":[3.610044025],"iteration":661,"passed_time":0.39256803,"remaining_time":0.2004350364},
{"learn":[3.607342669],"iteration":662,"passed_time":0.3932838215,"remaining_time":0.1999044462},
{"learn":[3.602510618],"iteration":663,"passed_time":0.3938803075,"remaining_time":0.1993129267},
{"learn":[3.600492392],"iteration":664,"passed_time":0.3944477147,"remaining_time":0.1987067435},
{"learn":[3.597171065],"iteration":665,"passed_time":0.39505332,"remaining_time":0.1981198332},
{"learn":[3.594358798],"iteration":666,"passed_time":0.3956921246,"remaining_time":0.1975494415},
{"learn":[3.593945251],"iteration":667,"passed_time":0.3962448739,"remaining_time":0.1969360751},
{"learn":[3.593607748],"iteration":668,"passed_time":0.3968224596,"remaining_time":0.1963351781},
{"learn":[3.592238714],"iteration":669,"passed_time":0.3973665901,"remaining_time":0.1957178727},
{"learn":[3.590144654],"iteration":670,"passed_time":0.3978585316,"remaining_time":0.1950751966},
{"learn":[3.587151536],"iteration":671,"passed_time":0.3983448103,"remaining_time":0.194430205},
{"learn":[3.586070865],"iteration":672,"passed_time":0.3988193699,"remaining_time":0.193779991},
{"learn":[3.585102746],"iteration":673,"passed_time":0.3993052475,"remaining_time":0.1931357725},
{"learn":[3.584362847],"iteration":674,"passed_time":0.3997734033,"remaining_time":0.1924834905},
{"learn":[3.581407561],"iteration":675,"passed_time":0.4003039265,"remaining_time":0.1918616453},
{"learn":[3.57919422],"iteration":676,"passed_time":0.4008162546,"remaining_time":0.1912313888},
{"learn":[3.577632204],"iteration":677,"passed_time":0.4012890962,"remaining_time":0.1905827271},
{"learn":[3.573911195],"iteration":678,"passed_time":0.4017610944,"remaining_time":0.1899341845},
{"learn":[3.573408216],"iteration":679,"passed_time":0.4022109924,"remaining_time":0.1892757611},
{"learn":[3.571076482],"iteration":680,"passed_time":0.4027015642,"remaining_time":0.1886370029},
{"learn":[3.568177107],"iteration":681,"passed_time":0.4032385002,"remaining_time":0.1880202978},
{"learn":[3.564824621],"iteration":682,"passed_time":0.4037727564,"remaining_time":0.1874025824},
{"learn":[3.562475026],"iteration":683,"passed_time":0.4043434413,"remaining_time":0.1868019407},
{"learn":[3.561226889],"iteration":684,"passed_time":0.4055169332,"remaining_time":0.1864785897},
{"learn":[3.559383467],"iteration":685,"passed_time":0.4062788848,"remaining_time":0.1859643875},
{"learn":[3.555209766],"iteration":686,"passed_time":0.406882667,"remaining_time":0.1853774014},
{"learn":[3.55345383],"iteration":687,"passed_time":0.4074536386,"remaining_time":0.1847754873},
{"learn":[3.552300968],"iteration":688,"passed_time":0.4089729529,"remaining_time":0.1846017248},
{"learn":[3.551253986],"iteration":689,"passed_time":0.4094806426,"remaining_time":0.183969564},
{"learn":[3.549807725],"iteration":690,"passed_time":0.4099853386,"remaining_time":0.1833364249},
{"learn":[3.547992926],"iteration":691,"passed_time":0.4105839337,"remaining_time":0.1827454503},
{"learn":[3.545438607],"iteration":692,"passed_time":0.4112267935,"remaining_time":0.1821740629},
{"learn":[3.543313763],"iteration":693,"passed_time":0.4118294544,"remaining_time":0.181584745},
{"learn":[3.542962896],"iteration":694,"passed_time":0.4123812812,"remaining_time":0.1809730802},
{"learn":[3.539800465],"iteration":695,"passed_time":0.412842209,"remaining_time":0.1803218844},
{"learn":[3.53953187],"iteration":696,"passed_time":0.4133499137,"remaining_time":0.1796915694},
{"learn":[3.536332425],"iteration":697,"passed_time":0.4138514881,"remaining_time":0.1790589533},
{"learn":[3.534993327],"iteration":698,"passed_time":0.414344651,"remaining_time":0.17842309},
{"learn":[3.531637011],"iteration":699,"passed_time":0.4148586651,"remaining_time":0.1777965708},
{"learn":[3.531040284],"iteration":700,"passed_time":0.4153116321,"remaining_time":0.1771443338},
{"learn":[3.529973872],"iteration":701,"passed_time":0.4166282163,"remaining_time":0.1768592713},
{"learn":[3.527325183],"iteration":702,"passed_time":0.4172889685,"remaining_time":0.1762942015},
{"learn":[3.527200815],"iteration":703,"passed_time":0.4178054708,"remaining_time":0.1756682093},
{"learn":[3.523459911],"iteration":704,"passed_time":0.418353015,"remaining_time":0.1750555169},
{"learn":[3.522729934],"iteration":705,"passed_time":0.4190371443,"remaining_time":0.1744998873},
{"learn":[3.522260582],"iteration":706,"passed_time":0.4199003043,"remaining_time":0.1740180893},
{"learn":[3.518641591],"iteration":707,"passed_time":0.4205407793,"remaining_time":0.1734433723},
{"learn":[3.516856405],"iteration":708,"passed_time":0.4211293034,"remaining_time":0.1728471471},
{"learn":[3.515083413],"iteration":709,"passed_time":0.4216243546,"remaining_time":0.1722127645},
{"learn":[3.514671214],"iteration":710,"passed_time":0.4222451317,"remaining_time":0.1716298777},
{"learn":[3.512617621],"iteration":711,"passed_time":0.4228483744,"remaining_time":0.1710397919},
{"learn":[3.510747971],"iteration":712,"passed_time":0.4234462437,"remaining_time":0.1704475062},
{"learn":[3.508149266],"iteration":713,"passed_time":0.4240358886,"remaining_time":0.1698519106},
{"learn":[3.504557165],"iteration":714,"passed_time":0.4246536626,"remaining_time":0.1692675439},
{"learn":[3.501367208],"iteration":715,"passed_time":0.4252647613,"remaining_time":0.168680436},
{"learn":[3.497593362],"iteration":716,"passed_time":0.4258625101,"remaining_time":0.1680879921},
{"learn":[3.496291169],"iteration":717,"passed_time":0.4281801335,"remaining_time":0.1681710274},
{"learn":[3.49330374],"iteration":718,"passed_time":0.4286745688,"remaining_time":0.1675348454},
{"learn":[3.490044385],"iteration":719,"passed_time":0.4292785187,"remaining_time":0.1669416462},
{"learn":[3.488891789],"iteration":720,"passed_time":0.4297918492,"remaining_time":0.1663133508},
{"learn":[3.486869081],"iteration":721,"passed_time":0.4302444783,"remaining_time":0.1656620014},
{"learn":[3.486303638],"iteration":722,"passed_time":0.4307146319,"remaining_time":0.1650179157},
{"learn":[3.486035862],"iteration":723,"passed_time":0.431167763,"remaining_time":0.1643678213},
{"learn":[3.482668951],"iteration":724,"passed_time":0.4316347624,"remaining_time":0.1637235306},
{"learn":[3.47820549],"iteration":725,"passed_time":0.4321499551,"remaining_time":0.1630979169},
{"learn":[3.474392283],"iteration":726,"passed_time":0.4328012707,"remaining_time":0.1625237234},
{"learn":[3.472268163],"iteration":727,"passed_time":0.4355289035,"remaining_time":0.1627250848},
{"learn":[3.471209164],"iteration":728,"passed_time":0.4361583066,"remaining_time":0.1621384103},
{"learn":[3.470049971],"iteration":729,"passed_time":0.4366794328,"remaining_time":0.161511571},
{"learn":[3.469078654],"iteration":730,"passed_time":0.4372491244,"remaining_time":0.1609028926},
{"learn":[3.468643292],"iteration":731,"passed_time":0.4378768605,"remaining_time":0.1603155719},
{"learn":[3.468134848],"iteration":732,"passed_time":0.4385599839,"remaining_time":0.1597483161},
{"learn":[3.467820182],"iteration":733,"passed_time":0.4391822378,"remaining_time":0.1591586856},
{"learn":[3.465776156],"iteration":734,"passed_time":0.4397612329,"remaining_time":0.1585533697},
{"learn":[3.463037608],"iteration":735,"passed_time":0.4403118174,"remaining_time":0.1579379345},
{"learn":[3.45965637],"iteration":736,"passed_time":0.440871072,"remaining_time":0.1573257692},
{"learn":[3.457275091],"iteration":737,"passed_time":0.4414296384,"remaining_time":0.1567135031},
{"learn":[3.455522955],"iteration":738,"passed_time":0.4419551276,"remaining_time":0.1560897},
{"learn":[3.451270508],"iteration":739,"passed_time":0.4426126332,"remaining_time":0.1555125468},
{"learn":[3.450978947],"iteration":740,"passed_time":0.4431650693,"remaining_time":0.154898452},
{"learn":[3.450608492],"iteration":741,"passed_time":0.4436731695,"remaining_time":0.1542691075},
{"learn":[3.448122004],"iteration":742,"passed_time":0.4442150799,"remaining_time":0.153651784},
{"learn":[3.445646714],"iteration":743,"passed_time":0.4447699966,"remaining_time":0.1530391386},
{"learn":[3.44411263],"iteration":744,"passed_time":0.445287159,"remaining_time":0.1524137256},
{"learn":[3.443264164],"iteration":745,"passed_time":0.4458516193,"remaining_time":0.1518047068},
{"learn":[3.439521363],"iteration":746,"passed_time":0.4463295872,"remaining_time":0.1511665135},
{"learn":[3.436809225],"iteration":747,"passed_time":0.4468100769,"remaining_time":0.1505295981},
{"learn":[3.435509465],"iteration":748,"passed_time":0.4478575566,"remaining_time":0.1500831064},
{"learn":[3.434450277],"iteration":749,"passed_time":0.4487449069,"remaining_time":0.1495816356},
{"learn":[3.431786753],"iteration":750,"passed_time":0.4499796448,"remaining_time":0.1491943163},
{"learn":[3.430150302],"iteration":751,"passed_time":0.4505239389,"remaining_time":0.1485770437},
{"learn":[3.42696281],"iteration":752,"passed_time":0.4510359352,"remaining_time":0.1479493705},
{"learn":[3.426870334],"iteration":753,"passed_time":0.4516789832,"remaining_time":0.1473647611},
{"learn":[3.425200309],"iteration":754,"passed_time":0.4526045879,"remaining_time":0.1468716875},
{"learn":[3.423383783],"iteration":755,"passed_time":0.4532032167,"remaining_time":0.1462719377},
{"learn":[3.422752979],"iteration":756,"passed_time":0.4537587614,"remaining_time":0.1456583607},
{"learn":[3.420845924],"iteration":757,"passed_time":0.4542909977,"remaining_time":0.1450374953},
{"learn":[3.418917862],"iteration":758,"passed_time":0.4549017389,"remaining_time":0.1444417906},
{"learn":[3.417095735],"iteration":759,"passed_time":0.4554806879,"remaining_time":0.1438360067},
{"learn":[3.414391848],"iteration":760,"passed_time":0.4561607991,"remaining_time":0.1432620644},
{"learn":[3.41426711],"iteration":761,"passed_time":0.4566778516,"remaining_time":0.1426369143},
{"learn":[3.411976013],"iteration":762,"passed_time":0.4571885785,"remaining_time":0.1420100827},
{"learn":[3.408614844],"iteration":763,"passed_time":0.457729252,"remaining_time":0.1413928056},
{"learn":[3.407906721],"iteration":764,"passed_time":0.458264868,"remaining_time":0.1407741751},
{"learn":[3.407494015],"iteration":765,"passed_time":0.4588102468,"remaining_time":0.1401587438},
{"learn":[3.406287128],"iteration":766,"passed_time":0.4592736773,"remaining_time":0.1395186008},
{"learn":[3.404600442],"iteration":767,"passed_time":0.4598106168,"remaining_time":0.1389011238},
{"learn":[3.404012662],"iteration":768,"passed_time":0.4602772222,"remaining_time":0.1382627286},
{"learn":[3.400398762],"iteration":769,"passed_time":0.4607734785,"remaining_time":0.1376336364},
{"learn":[3.399737714],"iteration":770,"passed_time":0.4612800432,"remaining_time":0.1370079506},
{"learn":[3.399185251],"iteration":771,"passed_time":0.4617901116,"remaining_time":0.1363836081},
{"learn":[3.397245411],"iteration":772,"passed_time":0.4623228609,"remaining_time":0.1357662218},
{"learn":[3.396229831],"iteration":773,"passed_time":0.4630814751,"remaining_time":0.1352150043},
{"learn":[3.394002836],"iteration":774,"passed_time":0.4642441149,"remaining_time":0.1347805495},
{"learn":[3.389617243],"iteration":775,"passed_time":0.4648259631,"remaining_time":0.1341765667},
{"learn":[3.385426488],"iteration":776,"passed_time":0.465350612,"remaining_time":0.1335562245},
{"learn":[3.385072258],"iteration":777,"passed_time":0.4658689213,"remaining_time":0.1329343194},
{"learn":[3.383842366],"iteration":778,"passed_time":0.4672819907,"remaining_time":0.1325665211},
{"learn":[3.380110746],"iteration":779,"passed_time":0.4678557691,"remaining_time":0.1319593195},
{"learn":[3.378595218],"iteration":780,"passed_time":0.4684270985,"remaining_time":0.1313515167},
{"learn":[3.377371219],"iteration":781,"passed_time":0.4690096052,"remaining_time":0.1307469232},
{"learn":[3.375814782],"iteration":782,"passed_time":0.4696126888,"remaining_time":0.1301480887},
{"learn":[3.374195887],"iteration":783,"passed_time":0.4702355837,"remaining_time":0.1295547016},
{"learn":[3.373704309],"iteration":784,"passed_time":0.470754674,"remaining_time":0.1289328088},
{"learn":[3.372971757],"iteration":785,"passed_time":0.4712968524,"remaining_time":0.1283174636},
{"learn":[3.371565136],"iteration":786,"passed_time":0.4718895773,"remaining_time":0.1277159847},
{"learn":[3.3700309],"iteration":787,"passed_time":0.4723979576,"remaining_time":0.1270918363},
{"learn":[3.368186663],"iteration":788,"passed_time":0.4728990747,"remaining_time":0.126466039},
{"learn":[3.366710398],"iteration":789,"passed_time":0.4733851736,"remaining_time":0.1258365651},
{"learn":[3.364598042],"iteration":790,"passed_time":0.4738552439,"remaining_time":0.1252032187},
{"learn":[3.36348442],"iteration":791,"passed_time":0.4742712269,"remaining_time":0.1245560798},
{"learn":[3.362001759],"iteration":792,"passed_time":0.4746767148,"remaining_time":0.1239067843},
{"learn":[3.361580401],"iteration":793,"passed_time":0.4750556125,"remaining_time":0.1232512043},
{"learn":[3.359543675],"iteration":794,"passed_time":0.4755382028,"remaining_time":0.1226230586},
{"learn":[3.35766119],"iteration":795,"passed_time":0.4760045085,"remaining_time":0.1219911052},
{"learn":[3.354592969],"iteration":796,"passed_time":0.4765175268,"remaining_time":0.1213714654},
{"learn":[3.350985986],"iteration":797,"passed_time":0.4771138024,"remaining_time":0.120773168},
{"learn":[3.349589624],"iteration":798,"passed_time":0.4778641736,"remaining_time":0.1202136407},
{"learn":[3.349110856],"iteration":799,"passed_time":0.478993958,"remaining_time":0.1197484895},
{"learn":[3.345315441],"iteration":800,"passed_time":0.4795679824,"remaining_time":0.1191436061},
{"learn":[3.34397474],"iteration":801,"passed_time":0.4801913164,"remaining_time":0.1185509734},
{"learn":[3.343800902],"iteration":802,"passed_time":0.4808227615,"remaining_time":0.1179602541},
{"learn":[3.342329465],"iteration":803,"passed_time":0.4813873256,"remaining_time":0.1173531291},
{"learn":[3.34220347],"iteration":804,"passed_time":0.4820644242,"remaining_time":0.1167733698},
{"learn":[3.341279219],"iteration":805,"passed_time":0.4826370326,"remaining_time":0.1161682188},
{"learn":[3.337329521],"iteration":806,"passed_time":0.4831676592,"remaining_time":0.1155531081},
{"learn":[3.336708453],"iteration":807,"passed_time":0.4837521862,"remaining_time":0.1149510146},
{"learn":[3.333252703],"iteration":808,"passed_time":0.4843333016,"remaining_time":0.114348159},
{"learn":[3.332186769],"iteration":809,"passed_time":0.484883738,"remaining_time":0.1137381608},
{"learn":[3.330594851],"iteration":810,"passed_time":0.4854393434,"remaining_time":0.1131295141},
{"learn":[3.327867442],"iteration":811,"passed_time":0.4859999729,"remaining_time":0.1125221612},
{"learn":[3.327563111],"iteration":812,"passed_time":0.4864748548,"remaining_time":0.1118952003},
{"learn":[3.326308994],"iteration":813,"passed_time":0.4869363864,"remaining_time":0.1112655625},
{"learn":[3.326249879],"iteration":814,"passed_time":0.4873893308,"remaining_time":0.110634388},
{"learn":[3.322336238],"iteration":815,"passed_time":0.48790386,"remaining_time":0.110017537},
{"learn":[3.320491154],"iteration":816,"passed_time":0.4883759807,"remaining_time":0.1093914375},
{"learn":[3.320434271],"iteration":817,"passed_time":0.4888388375,"remaining_time":0.1087636533},
{"learn":[3.319609638],"iteration":818,"passed_time":0.4893327944,"remaining_time":0.108143145},
{"learn":[3.316182682],"iteration":819,"passed_time":0.489810968,"remaining_time":0.1075194808},
{"learn":[3.313126612],"iteration":820,"passed_time":0.490292817,"remaining_time":0.1068969723},
{"learn":[3.311222803],"iteration":821,"passed_time":0.4907979959,"remaining_time":0.106279858},
{"learn":[3.309627335],"iteration":822,"passed_time":0.4913467909,"remaining_time":0.1056723961},
{"learn":[3.307974895],"iteration":823,"passed_time":0.4936699322,"remaining_time":0.1054440632},
{"learn":[3.307321505],"iteration":824,"passed_time":0.4942508202,"remaining_time":0.1048410831},
{"learn":[3.306759087],"iteration":825,"passed_time":0.4947902811,"remaining_time":0.1042294297},
{"learn":[3.30484037],"iteration":826,"passed_time":0.495422857,"remaining_time":0.1036374296},
{"learn":[3.30201994],"iteration":827,"passed_time":0.4960737117,"remaining_time":0.1030491285},
{"learn":[3.299302297],"iteration":828,"passed_time":0.4966253709,"remaining_time":0.1024402152},
{"learn":[3.298132671],"iteration":829,"passed_time":0.4971764668,"remaining_time":0.1018313245},
{"learn":[3.296976183],"iteration":830,"passed_time":0.497754184,"remaining_time":0.1012279869},
{"learn":[3.293144745],"iteration":831,"passed_time":0.4984085956,"remaining_time":0.1006401972},
{"learn":[3.290284404],"iteration":832,"passed_time":0.4989690694,"remaining_time":0.1000334149},
{"learn":[3.288285745],"iteration":833,"passed_time":0.4994850698,"remaining_time":0.09941789159},
{"learn":[3.286662667],"iteration":834,"passed_time":0.499996907,"remaining_time":0.09880178402},
{"learn":[3.285692682],"iteration":835,"passed_time":0.5004710777,"remaining_time":0.09817853677},
{"learn":[3.284565611],"iteration":836,"passed_time":0.5009465599,"remaining_time":0.09755590115},
{"learn":[3.283897383],"iteration":837,"passed_time":0.5014341516,"remaining_time":0.09693595771},
{"learn":[3.280712855],"iteration":838,"passed_time":0.5019417916,"remaining_time":0.09632017693},
{"learn":[3.280468341],"iteration":839,"passed_time":0.5023775101,"remaining_time":0.09569095431},
{"learn":[3.277814895],"iteration":840,"passed_time":0.5028686958,"remaining_time":0.09507267851},
{"learn":[3.276316385],"iteration":841,"passed_time":0.5033421406,"remaining_time":0.09445137556},
{"learn":[3.27557063],"iteration":842,"passed_time":0.5038226428,"remaining_time":0.09383173775},
{"learn":[3.27499628],"iteration":843,"passed_time":0.5042721624,"remaining_time":0.09320670301},
{"learn":[3.273569958],"iteration":844,"passed_time":0.5048963177,"remaining_time":0.09261411744},
{"learn":[3.269665595],"iteration":845,"passed_time":0.5054075099,"remaining_time":0.09200089424},
{"learn":[3.267984685],"iteration":846,"passed_time":0.5059421405,"remaining_time":0.09139214581},
{"learn":[3.267702508],"iteration":847,"passed_time":0.5065011702,"remaining_time":0.09078794561},
{"learn":[3.266671924],"iteration":848,"passed_time":0.5076105239,"remaining_time":0.0902817304},
{"learn":[3.265359825],"iteration":849,"passed_time":0.5082500186,"remaining_time":0.08969117976},
{"learn":[3.2618983],"iteration":850,"passed_time":0.5088153096,"remaining_time":0.0890875219},
{"learn":[3.260456253],"iteration":851,"passed_time":0.5093513156,"remaining_time":0.08847886702},
{"learn":[3.258389147],"iteration":852,"passed_time":0.5099161016,"remaining_time":0.08787534225},
{"learn":[3.258108469],"iteration":853,"passed_time":0.5104199709,"remaining_time":0.08726149386},
{"learn":[3.256424936],"iteration":854,"passed_time":0.510970067,"remaining_time":0.08665574236},
{"learn":[3.254817983],"iteration":855,"passed_time":0.5117125054,"remaining_time":0.08608247755},
{"learn":[3.253898449],"iteration":856,"passed_time":0.5122837485,"remaining_time":0.08548025208},
{"learn":[3.253023652],"iteration":857,"passed_time":0.5128586769,"remaining_time":0.08487870876},
{"learn":[3.252845542],"iteration":858,"passed_time":0.5134522787,"remaining_time":0.08428029254},
{"learn":[3.252316026],"iteration":859,"passed_time":0.5139872466,"remaining_time":0.08367234246},
{"learn":[3.24975301],"iteration":860,"passed_time":0.5145320627,"remaining_time":0.08306615181},
{"learn":[3.249151075],"iteration":861,"passed_time":0.5150733797,"remaining_time":0.08245954339},
{"learn":[3.246257135],"iteration":862,"passed_time":0.5156161614,"remaining_time":0.08185331879},
{"learn":[3.243826471],"iteration":863,"passed_time":0.5160965121,"remaining_time":0.08123741393},
{"learn":[3.243190653],"iteration":864,"passed_time":0.5165989062,"remaining_time":0.08062526281},
{"learn":[3.24008797],"iteration":865,"passed_time":0.5170724489,"remaining_time":0.08000890087},
{"learn":[3.240036811],"iteration":866,"passed_time":0.5175533572,"remaining_time":0.07939399828},
{"learn":[3.238676314],"iteration":867,"passed_time":0.5180336185,"remaining_time":0.07877930603},
{"learn":[3.237848782],"iteration":868,"passed_time":0.5185611666,"remaining_time":0.07817205158},
{"learn":[3.236405498],"iteration":869,"passed_time":0.5190305417,"remaining_time":0.07755628784},
{"learn":[3.233378068],"iteration":870,"passed_time":0.5195248163,"remaining_time":0.07694454799},
{"learn":[3.233169169],"iteration":871,"passed_time":0.5199762864,"remaining_time":0.07632679434},
{"learn":[3.232434885],"iteration":872,"passed_time":0.520555003,"remaining_time":0.07572793285},
{"learn":[3.229978115],"iteration":873,"passed_time":0.5212095702,"remaining_time":0.07514005245},
{"learn":[3.229648848],"iteration":874,"passed_time":0.5222436821,"remaining_time":0.0746062403},
{"learn":[3.227208761],"iteration":875,"passed_time":0.5229148943,"remaining_time":0.07401991655},
{"learn":[3.226258869],"iteration":876,"passed_time":0.523467465,"remaining_time":0.07341675963},
{"learn":[3.225331995],"iteration":877,"passed_time":0.5239946793,"remaining_time":0.07281019462},
{"learn":[3.221968268],"iteration":878,"passed_time":0.524526618,"remaining_time":0.0722044605},
{"learn":[3.221166317],"iteration":879,"passed_time":0.5250969199,"remaining_time":0.07160412545},
{"learn":[3.220047503],"iteration":880,"passed_time":0.5257675379,"remaining_time":0.07101740863},
{"learn":[3.21982781],"iteration":881,"passed_time":0.5264135182,"remaining_time":0.07042720539},
{"learn":[3.216693405],"iteration":882,"passed_time":0.5269702541,"remaining_time":0.06982505065},
{"learn":[3.214798761],"iteration":883,"passed_time":0.5275252431,"remaining_time":0.06922276946},
{"learn":[3.214395085],"iteration":884,"passed_time":0.5280712217,"remaining_time":0.06861942429},
{"learn":[3.213470696],"iteration":885,"passed_time":0.5285936761,"remaining_time":0.0680131818},
{"learn":[3.211595017],"iteration":886,"passed_time":0.5291362139,"remaining_time":0.06740968677},
{"learn":[3.210965255],"iteration":887,"passed_time":0.5296644467,"remaining_time":0.06680452481},
{"learn":[3.209413583],"iteration":888,"passed_time":0.5301540818,"remaining_time":0.06619471663},
{"learn":[3.208331683],"iteration":889,"passed_time":0.5306438003,"remaining_time":0.0655851888},
{"learn":[3.207110711],"iteration":890,"passed_time":0.5311163481,"remaining_time":0.06497382935},
{"learn":[3.204519413],"iteration":891,"passed_time":0.5316374719,"remaining_time":0.06436866251},
{"learn":[3.201421296],"iteration":892,"passed_time":0.5321502046,"remaining_time":0.06376267849},
{"learn":[3.200691259],"iteration":893,"passed_time":0.5326389503,"remaining_time":0.06315405898},
{"learn":[3.200485067],"iteration":894,"passed_time":0.533422353,"remaining_time":0.06258027605},
{"learn":[3.197467568],"iteration":895,"passed_time":0.5339333846,"remaining_time":0.06197441071},
{"learn":[3.195838544],"iteration":896,"passed_time":0.5344354299,"remaining_time":0.06136772495},
{"learn":[3.195671746],"iteration":897,"passed_time":0.534958723,"remaining_time":0.06076368569},
{"learn":[3.194213094],"iteration":898,"passed_time":0.5354933491,"remaining_time":0.06016109929},
{"learn":[3.192884691],"iteration":899,"passed_time":0.5363877327,"remaining_time":0.05959863697},
{"learn":[3.188364239],"iteration":900,"passed_time":0.5371156152,"remaining_time":0.05901714307},
{"learn":[3.185219478],"iteration":901,"passed_time":0.5377230832,"remaining_time":0.05842224186},
{"learn":[3.184120387],"iteration":902,"passed_time":0.5382421655,"remaining_time":0.05781781845},
{"learn":[3.183725321],"iteration":903,"passed_time":0.5388314722,"remaining_time":0.05722104129},
{"learn":[3.181264554],"iteration":904,"passed_time":0.5395370848,"remaining_time":0.05663648956},
{"learn":[3.180741589],"iteration":905,"passed_time":0.5402245836,"remaining_time":0.05604979124},
{"learn":[3.179782639],"iteration":906,"passed_time":0.5408407213,"remaining_time":0.05545555356},
{"learn":[3.176377564],"iteration":907,"passed_time":0.5413745598,"remaining_time":0.05485292897},
{"learn":[3.174078182],"iteration":908,"passed_time":0.5419391617,"remaining_time":0.05425353544},
{"learn":[3.171242379],"iteration":909,"passed_time":0.5424995562,"remaining_time":0.05365380226},
{"learn":[3.170421012],"iteration":910,"passed_time":0.5430552846,"remaining_time":0.05305369959},
{"learn":[3.170087224],"iteration":911,"passed_time":0.5436185568,"remaining_time":0.05245442214},
{"learn":[3.167303059],"iteration":912,"passed_time":0.5441370664,"remaining_time":0.05185095813},
{"learn":[3.16705966],"iteration":913,"passed_time":0.54462271,"remaining_time":0.05124458759},
{"learn":[3.165667683],"iteration":914,"passed_time":0.5451983135,"remaining_time":0.05064683787},
{"learn":[3.164689733],"iteration":915,"passed_time":0.5457038603,"remaining_time":0.05004271208},
{"learn":[3.163311455],"iteration":916,"passed_time":0.546245475,"remaining_time":0.0494420659},
{"learn":[3.159425016],"iteration":917,"passed_time":0.5467343773,"remaining_time":0.0488368398},
{"learn":[3.159327058],"iteration":918,"passed_time":0.5472318398,"remaining_time":0.04823262135},
{"learn":[3.15819426],"iteration":919,"passed_time":0.5477255056,"remaining_time":0.04762830483},
{"learn":[3.157086603],"iteration":920,"passed_time":0.5482063531,"remaining_time":0.04702312909},
{"learn":[3.153354154],"iteration":921,"passed_time":0.5486596147,"remaining_time":0.04641588931},
{"learn":[3.153261317],"iteration":922,"passed_time":0.5491673164,"remaining_time":0.04581352477},
{"learn":[3.153168454],"iteration":923,"passed_time":0.5497170169,"remaining_time":0.04521481957},
{"learn":[3.152080399],"iteration":924,"passed_time":0.5507761127,"remaining_time":0.04465752265},
{"learn":[3.151635144],"iteration":925,"passed_time":0.5516074177,"remaining_time":0.04408093835},
{"learn":[3.147762655],"iteration":926,"passed_time":0.5521589459,"remaining_time":0.04348177244},
{"learn":[3.147172317],"iteration":927,"passed_time":0.5526607873,"remaining_time":0.04287885419},
{"learn":[3.146254125],"iteration":928,"passed_time":0.5532273648,"remaining_time":0.04228110108},
{"learn":[3.144869828],"iteration":929,"passed_time":0.5538286032,"remaining_time":0.0416860239},
{"learn":[3.143466218],"iteration":930,"passed_time":0.554484624,"remaining_time":0.04109499362},
{"learn":[3.141919643],"iteration":931,"passed_time":0.5550252956,"remaining_time":0.04049540783},
{"learn":[3.141054135],"iteration":932,"passed_time":0.555618677,"remaining_time":0.0398997335},
{"learn":[3.139390417],"iteration":933,"passed_time":0.5561683871,"remaining_time":0.0393009781},
{"learn":[3.139025283],"iteration":934,"passed_time":0.5567205928,"remaining_time":0.0387025011},
{"learn":[3.137824183],"iteration":935,"passed_time":0.5573049051,"remaining_time":0.0381063183},
{"learn":[3.135620453],"iteration":936,"passed_time":0.5578517771,"remaining_time":0.0375076435},
{"learn":[3.13443178],"iteration":937,"passed_time":0.5583787571,"remaining_time":0.03690776433},
{"learn":[3.132765713],"iteration":938,"passed_time":0.5589704198,"remaining_time":0.0363122424},
{"learn":[3.131434124],"iteration":939,"passed_time":0.55949397,"remaining_time":0.03571238106},
{"learn":[3.128384262],"iteration":940,"passed_time":0.5600280404,"remaining_time":0.03511334154},
{"learn":[3.128120455],"iteration":941,"passed_time":0.5605073199,"remaining_time":0.03451106641},
{"learn":[3.126314615],"iteration":942,"passed_time":0.5609824463,"remaining_time":0.0339088011},
{"learn":[3.125409666],"iteration":943,"passed_time":0.5614067792,"remaining_time":0.03330379199},
{"learn":[3.123072589],"iteration":944,"passed_time":0.5618326059,"remaining_time":0.03269925219},
{"learn":[3.122921099],"iteration":945,"passed_time":0.5622143215,"remaining_time":0.03209257227},
{"learn":[3.122182662],"iteration":946,"passed_time":0.5625989937,"remaining_time":0.03148653291},
{"learn":[3.120040951],"iteration":947,"passed_time":0.5630069365,"remaining_time":0.03088223702},
{"learn":[3.118767799],"iteration":948,"passed_time":0.5634724848,"remaining_time":0.03028145071},
{"learn":[3.118203218],"iteration":949,"passed_time":0.5640470663,"remaining_time":0.0296866877},
{"learn":[3.116343362],"iteration":950,"passed_time":0.5646705253,"remaining_time":0.02909448553},
{"learn":[3.11480829],"iteration":951,"passed_time":0.5656365387,"remaining_time":0.02851948935},
{"learn":[3.112607903],"iteration":952,"passed_time":0.5663412809,"remaining_time":0.0279307872},
{"learn":[3.111661241],"iteration":953,"passed_time":0.566889703,"remaining_time":0.02733430434},
{"learn":[3.110249676],"iteration":954,"passed_time":0.5674616318,"remaining_time":0.02673902977},
{"learn":[3.107333579],"iteration":955,"passed_time":0.5680788576,"remaining_time":0.02614588885},
{"learn":[3.107149851],"iteration":956,"passed_time":0.5686565683,"remaining_time":0.02555092209},
{"learn":[3.106867336],"iteration":957,"passed_time":0.5692388462,"remaining_time":0.02495619159},
{"learn":[3.10364681],"iteration":958,"passed_time":0.5698505983,"remaining_time":0.02436274716},
{"learn":[3.102703811],"iteration":959,"passed_time":0.5703752116,"remaining_time":0.02376563382},
{"learn":[3.101469264],"iteration":960,"passed_time":0.5709298548,"remaining_time":0.02316989005},
{"learn":[3.09863569],"iteration":961,"passed_time":0.5715691698,"remaining_time":0.02257757635},
{"learn":[3.09645939],"iteration":962,"passed_time":0.5720789395,"remaining_time":0.02198018771},
{"learn":[3.096240186],"iteration":963,"passed_time":0.5725643819,"remaining_time":0.02138207235},
{"learn":[3.094838828],"iteration":964,"passed_time":0.5730676464,"remaining_time":0.02078483692},
{"learn":[3.094176802],"iteration":965,"passed_time":0.5735433917,"remaining_time":0.02018682745},
{"learn":[3.093182279],"iteration":966,"passed_time":0.5740426265,"remaining_time":0.01958987247},
{"learn":[3.090150687],"iteration":967,"passed_time":0.5745564745,"remaining_time":0.01899360246},
{"learn":[3.088612829],"iteration":968,"passed_time":0.5750673691,"remaining_time":0.01839740809},
{"learn":[3.087153684],"iteration":969,"passed_time":0.5755351103,"remaining_time":0.01780005496},
{"learn":[3.085866843],"iteration":970,"passed_time":0.5760123619,"remaining_time":0.01720325283},
{"learn":[3.082669094],"iteration":971,"passed_time":0.5765137597,"remaining_time":0.01660739225},
{"learn":[3.081047548],"iteration":972,"passed_time":0.5770063212,"remaining_time":0.01601148065},
{"learn":[3.079684322],"iteration":973,"passed_time":0.577513412,"remaining_time":0.01541616911},
{"learn":[3.07613431],"iteration":974,"passed_time":0.5780223705,"remaining_time":0.01482108642},
{"learn":[3.074005935],"iteration":975,"passed_time":0.5785808205,"remaining_time":0.01422739723},
{"learn":[3.072988853],"iteration":976,"passed_time":0.5791444179,"remaining_time":0.01363390134},
{"learn":[3.072344268],"iteration":977,"passed_time":0.5802504954,"remaining_time":0.01305266963},
{"learn":[3.070654438],"iteration":978,"passed_time":0.5808412793,"remaining_time":0.01245931243},
{"learn":[3.069724506],"iteration":979,"passed_time":0.5814254706,"remaining_time":0.01186582593},
{"learn":[3.067763166],"iteration":980,"passed_time":0.5819824925,"remaining_time":0.01127183217},
{"learn":[3.066737893],"iteration":981,"passed_time":0.5825789313,"remaining_time":0.01067863621},
{"learn":[3.065248174],"iteration":982,"passed_time":0.5832162626,"remaining_time":0.01008614086},
{"learn":[3.063186837],"iteration":983,"passed_time":0.5838661281,"remaining_time":0.00949375818},
{"learn":[3.062880371],"iteration":984,"passed_time":0.5844823711,"remaining_time":0.008900746769},
{"learn":[3.061288645],"iteration":985,"passed_time":0.585133515,"remaining_time":0.008308183784},
{"learn":[3.059970575],"iteration":986,"passed_time":0.585719945,"remaining_time":0.007714649732},
{"learn":[3.059576341],"iteration":987,"passed_time":0.586259699,"remaining_time":0.007120563146},
{"learn":[3.058175919],"iteration":988,"passed_time":0.586780629,"remaining_time":0.006526377066},
{"learn":[3.056830702],"iteration":989,"passed_time":0.5874853702,"remaining_time":0.005934195659},
{"learn":[3.056336579],"iteration":990,"passed_time":0.5879774784,"remaining_time":0.00533985601},
{"learn":[3.055810414],"iteration":991,"passed_time":0.588507461,"remaining_time":0.004746027911},
{"learn":[3.055476518],"iteration":992,"passed_time":0.5890246068,"remaining_time":0.004152237913},
{"learn":[3.053331734],"iteration":993,"passed_time":0.5895188102,"remaining_time":0.003558463643},
{"learn":[3.050890374],"iteration":994,"passed_time":0.5899929673,"remaining_time":0.00296478878},
{"learn":[3.04972623],"iteration":995,"passed_time":0.5905461523,"remaining_time":0.002371671294},
{"learn":[3.047217327],"iteration":996,"passed_time":0.5910444224,"remaining_time":0.001778468673},
{"learn":[3.047155483],"iteration":997,"passed_time":0.5915239489,"remaining_time":0.001185418735},
{"learn":[3.04430671],"iteration":998,"passed_time":0.5930438149,"remaining_time":0.0005936374523},
{"learn":[3.042664195],"iteration":999,"passed_time":0.5940782174,"remaining_time":0}
]}